Workbook
Name SegmentaçãodeDados_ANO_FIM: #N/A
Name SegmentaçãodeDados_ANO_FIM11: #N/A
Name SegmentaçãodeDados_BASE_REGIONAL1: #N/A
Name SegmentaçãodeDados_LOCADORA1: #N/A
Name SegmentaçãodeDados_MÊS_FIM: #N/A
Name SegmentaçãodeDados_MÊS_FIM11: #N/A
Name SegmentaçãodeDados_MODELO1: #N/A
Name SegmentaçãodeDados_OBSERVAÇÕES1: #N/A

Sheet TAB VENCIMENTOS (2)
A1: FILTROS
A16: ANALITICO
B18: MÊS FIM | C18: UF | D18: VENCIMENTO | F18: BASE REGIONAL | G18: TOTAL | I18: VEICULO TIPO | J18: TOTAL
B19: JAN | D19: 4 | F19: NORTE | G19: 12 | I19: 4X4 | J19: 7
C20: PR | D20: 2 | F20: SUDESTE | G20: 10 | I20: LEVE | J20: 20
C21: RS | D21: 2 | F21: SUL | G21: 10 | I21: UTILITARIO | J21: 5
B22: FEV | D22: 4 | F22: TOTAL | G22: 32 | I22: TOTAL | J22: 32
C23: SC | D23: 1
C24: SP | D24: 3
B25: MAR | D25: 22
C26: AM | D26: 5
C27: AP | D27: 7 | F27: QTDE POR LOCADORA | G27: TOTAL
C28: PR | D28: 2 | F28: LOCALIZA | G28: 32
C29: RS | D29: 1 | F29: FIORINO | G29: 3 | I29: QTD POR CLIENTE | J29: TOTAL
C30: SC | D30: 2 | F30: MOBI | G30: 20 | I30: 0 | J30: 1
C31: SP | D31: 5 | F31: S10 | G31: 7 | I31: ADMINISTRATIVO | J31: 2
B32: ABR | D32: 2 | F32: SAVEIRO | G32: 2 | I32: I-SYSTEMS | J32: 4
C33: SP | D33: 2 | F33: TOTAL GERAL | G33: 32 | I33: TIM MOVEL | J33: 10
B34: TOTAL | D34: 32 | I34: VIVO | J34: 15
I35: TOTAL | J35: 32

Sheet Planilha1
A3: Soma de DIAS
A4: Rótulos de Linha | B4: UF | C4: Status | D4: Veículo | E4: JANEIRO | F4: FEVEREIRO | G4: MARÇO | H4: ABRIL | I4: Total Geral
A5: MOVIDA | B5: AM | C5: MANUTENÇÃO | D5: SIF8C86 | H5: 11 | I5: 11
D6: SIF8C90 | H6: 26 | I6: 26
D7: SIF8D26 | H7: 18 | I7: 18
D8: SYH8A01 | H8: 13 | I8: 13
C9: SINISTRO | D9: SIK0I05 | E9: 98 | I9: 98
B10: DF | C10: MANUTENÇÃO | D10: PVR3F21 | H10: 26 | I10: 26
D11: PXS0F24 | F11: 60 | I11: 60
B12: ES | C12: MANUTENÇÃO | D12: SIK6J32 | G12: 29 | I12: 29
C13: SINISTRO | D13: SIY3G52 | F13: 59 | I13: 59
B14: GO | C14: SINISTRO | D14: SYH7H48 | H14: 7 | I14: 7
B15: MA | C15: MANUTENÇÃO | D15: SIK4H97 | G15: 39 | I15: 39
D16: SIK4I03 | H16: 21 | I16: 21
C17: SINISTRO | D17: SIY3H10 | H17: 12 | I17: 12
D18: SIY3H17 | E18: 111 | I18: 111
D19: SYH7H50 | G19: 42 | I19: 42
B20: MG | C20: MANUTENÇÃO | D20: PXS0E97 | G20: 54 | I20: 54
D21: PXS0F41 | I21: 131
D22: SIF8D23 | F22: 81 | I22: 81
D23: SYH7G06 | F23: 81 | I23: 81
C24: SINISTRO | D24: PVR9E41 | I24: 137
B25: MS | C25: MANUTENÇÃO | D25: TLI8G26 | H25: 21 | I25: 21
B26: MT | C26: MANUTENÇÃO | D26: TBW5A79 | H26: 19 | I26: 19
B27: PA | C27: MANUTENÇÃO | D27: SIY3G03 | H27: 12 | I27: 12
D28: SIY3G57 | H28: 24 | I28: 24
D29: SIY3H34 | H29: 11 | I29: 11
D30: SIY3H71 | H30: 24 | I30: 24
D31: SIY3H72 | H31: 13 | I31: 13
D32: TEY8D65 | H32: 19 | I32: 19
C33: SINISTRO | D33: SIK6J81 | H33: 19 | I33: 19
D34: SIK6J96 | H34: 24 | I34: 24
D35: SIK6J97 | H35: 8 | I35: 8
D36: SIK7A65 | H36: 24 | I36: 24
D37: SIY3G01 | H37: 17 | I37: 17
D38: SYH7F74 | F38: 84 | I38: 84
B39: RS | C39: MANUTENÇÃO | D39: PXS0E83 | G39: 53 | I39: 53
B40: SC | C40: SINISTRO | D40: SYH7H84 | H40: 12 | I40: 12
B41: TO | C41: MANUTENÇÃO | D41: PVR9E33 | G41: 32 | I41: 32
D42: SIK6J18 | H42: 17 | I42: 17
A43: Total Geral | E43: 209 | F43: 365 | G43: 249 | H43: 398 | I43: 1489

Sheet DIRETOR
A1: CARGO | B1: DIRETOR
A3: ÚLTIMO CONDUTOR | B3: GASTO COMBUSTÍVEL FEVEREIRO | C3: Soma de GASTO COMBUSTÍVE MARÇO | D3: Soma de GASTO COMBUSTÍVE ABRIL
A4: FABIO GONZAGA | B4: 1273.64 | C4: 2184.84 | D4: 1557.53
A5: FABIO TADEU SOLA | B5: 604.79 | C5: 691.39 | D5: 333.4
A6: MATHEUS RODRIGUES MONTE | B6: 1740.56 | C6: 773.37 | D6: 1903.35
A7: MARCELO VALLADA | B7: 495.44 | C7: 758.54 | D7: 265.02
A8: Total Geral | B8: 4114.43 | C8: 4408.14 | D8: 4059.3

Sheet GERENTE
A1: CARGO | B1: (Vários itens)
A3: NOME | B3: GASTO COMBUSTÍVEL FEVEREIRO | C3: Soma de GASTO COMBUSTÍVE MARÇO | D3: Soma de GASTO COMBUSTÍVE ABRIL
A4: ANDERSON JULIAN ESTEVÃO | B4: 920.95 | C4: 996.58 | D4: 279.81
A5: CLEITON DOS SANTOS DIAS MAIA | B5: 1520 | C5: 1845.12 | D5: 980
A6: DAVYS ROGÉRIO DA SILVA SANTOS | B6: 518.15 | C6: 707.29 | D6: 294.14
A7: DIOGO HENRIQUE MARCONDES | B7: 842.59 | C7: 690.64 | D7: 664.9
A8: DOUGLAS DE MELO SANCHEZ | B8: 1073.33 | C8: 1151.94 | D8: 1057.27
A9: EDSON BRUNO MORELATO | B9: 617.23 | C9: 909.84 | D9: 481.98
A10: FABIO LASCOSCH COSTA 21381013805 | B10: 1198.49 | C10: 1389.3 | D10: 231.43
A11: FELIPE SILVA SANTOS | B11: 1198.59 | C11: 1402.4 | D11: 729.19
A12: FERNANDA DE BARROS VILLAS BOAS | B12: 0 | C12: 0 | D12: 0
A13: JANDER JUNIOR INACIO PRATES | B13: 864.68 | C13: 1216.82 | D13: 1470.61
A14: JEFFERSON ALVES DE SOUZA | B14: 893.14 | C14: 1572.6 | D14: 0
A15: JHONATHAN DE OLIVEIRA CHAGAS | B15: 1900.89 | C15: 2682.24 | D15: 1118.09
... A30: Total Geral | B30: 27687.35 | C30: 34925.52 | D30: 15961.11

Sheet COORDENADOR
A1: CARGO | B1: (Vários itens)
A3: ÚLTIMO CONDUTOR | B3: Soma de GASTO COMBUSTÍVEL FEVEREIRO | C3: Soma de GASTO COMBUSTÍVE MARÇO | D3: Soma de GASTO COMBUSTÍVE ABRIL2
A4: ADEILTON DE SOUZA NAZARETH | B4: 1040 | C4: 800 | D4: 266.01
A5: ADEMIR TOMAZ DE MELO | B5: 2042.12 | C5: 1880.33 | D5: 935.21
A6: ADLER DE SOUSA LIMA | B6: 2165.58 | C6: 1384.25 | D6: 0
A7: ALEXANDRE VERAS RE | B7: 560.03 | C7: 896.31 | D7: 603.99
A8: ANA CRISTINA FREIRE HOLANDA | B8: 400 | C8: 1372.39 | D8: 625.11
A9: ANDRE GRANDIZOLI PERIGO MOURA | B9: 951.88 | C9: 583.61 | D9: 0
A10: CESAR AUGUSTO MELO HOENISCH | B10: 1355.71 | C10: 943.39 | D10: 132.85
A11: CLEVERSON DAMIAO GOMES | B11: 100 | C11: 1075.55 | D11: 1188.52
A12: DANIEL VICENTE FERREIRA | B12: 947.25 | C12: 1545.29 | D12: 403.11
A13: DAVID VIEIRA MAIA | B13: 1355.41 | C13: 2143.14 | D13: 899.84
A14: DENIS MARTINS DE OLIVEIRA | B14: 734.9 | C14: 862.21 | D14: 517.25
A15: EDMUR LUIZ FERREIRA DA SILVA | B15: 2233.39 | C15: 1993.33 | D15: 465.62
... A42: Total Geral | B42: 33877.1 | C42: 45168.76 | D42: 23425.87

Sheet TAB DE VENCIMENTO
A1: FILTRO | B1: VENCIDO
A2: LOCADORA | B2: (Vários itens) | L2: FILTRO | M2: ATENÇÃO | Q2: FILTRO | R2: VENCIDO
A4: ANO FIM | B4: MÊS FIM | C4: UF | D4: PLACA | E4: MODELO | F4: QTD | L4: CONTRATOS EM ATENÇÃO -3 MESES P/ VENC. | M4: . | Q4: VENCIDOS - RESUMO | R4: .
A5: 2024 | B5: SET | C5: AM | D5: RNJ0D35 | E5: MOBI | F5: 1 | L5: ANO | M5: LOCALIZA | N5: TOTAL | Q5: ANO | R5: LOCALIZA | S5: COMPANHIA DAS AMERICAS | T5: TOTAL
B6: SET | C6: AM | D6: RNJ0D85 | E6: MOBI | F6: 1 | L6: 2026 | Q6: 2025 | S6: 9 | T6: 9
B7: SET | C7: AM | D7: RNJ0E06 | E7: MOBI | F7: 1 | L7: MAI | Q7: RS | S7: 2 | T7: 2
B8: SET | C8: AM | D8: RNJ0E08 | E8: MOBI | F8: 1 | L8: MG | M8: 6 | N8: 6 | Q8: PR | S8: 7 | T8: 7
B9: SET | C9: AM | D9: RNJ0E47 | E9: MOBI | F9: 1 | L9: ES | M9: 3 | N9: 3 | Q9: 2026 | R9: 32 | T9: 32
B10: OUT | C10: AM | D10: RMT3C06 | E10: FIORINO | F10: 1 | L10: JUL | Q10: SP | R10: 10 | T10: 10
A11: 2025 | B11: NOV | C11: PR | D11: EGT8D42 | E11: SAVEIRO | F11: 1 | L11: ES | M11: 1 | N11: 1 | Q11: SC | R11: 3 | T11: 3
B12: NOV | C12: PR | D12: EJE2E81 | E12: SAVEIRO | F12: 1 | L12: TOTAL | M12: 10 | N12: 10 | Q12: RS | R12: 3 | T12: 3
B13: NOV | C13: PR | D13: EKU7H03 | E13: SAVEIRO | F13: 1 | Q13: PR | R13: 4 | T13: 4
B14: NOV | C14: PR | D14: ENI6B54 | E14: SAVEIRO | F14: 1 | Q14: AP | R14: 7 | T14: 7
B15: NOV | C15: PR | D15: EUC7H36 | E15: SAVEIRO | F15: 1 | Q15: AM | R15: 5 | T15: 5
B16: NOV | C16: PR | D16: EXJ4J06 | E16: SAVEIRO | F16: 1 | Q16: TOTAL | R16: 32 | S16: 9 | T16: 41
B17: NOV | C17: PR | D17: FJX1H02 | E17: SAVEIRO | F17: 1
B18: NOV | C18: RS | D18: EXH5C42 | E18: SAVEIRO | F18: 1
B19: NOV | C19: RS | D19: FLC7G24 | E19: SAVEIRO | F19: 1
A20: 2026 | B20: JAN | C20: PR | D20: RVS2F62 | E20: S10 | F20: 1
B21: JAN | C21: PR | D21: RVS2F70 | E21: S10 | F21: 1
B22: JAN | C22: RS | D22: RVS2F59 | E22: S10 | F22: 1
B23: JAN | C23: RS | D23: RVS2F68 | E23: S10 | F23: 1
B24: FEV | C24: SC | D24: SHD9F12 | E24: MOBI | F24: 1
B25: FEV | C25: SP | D25: SHD9C87 | E25: MOBI | F25: 1
B26: FEV | C26: SP | D26: SHD9F08 | E26: MOBI | F26: 1
B27: FEV | C27: SP | D27: SHD9F19 | E27: MOBI | F27: 1
B28: MAR | C28: AM | D28: SHG1G58 | E28: MOBI | F28: 1
B29: MAR | C29: AM | D29: SHG3G78 | E29: MOBI | F29: 1
B30: MAR | C30: AM | D30: SHG3G79 | E30: MOBI | F30: 1
B31: MAR | C31: AM | D31: SHG3G86 | E31: MOBI | F31: 1
B32: MAR | C32: AM | D32: SHG5J66 | E32: MOBI | F32: 1
... B51: ABR | C51: SP | D51: SHO6A62 | E51: FIORINO | F51: 1
A52: TOTAL | F52: 47

Sheet RELATORIO BASE
A1: PLACA | B1: MODELO | C1: TIPO | D1: ANO DO VEÍCULO | E1: LOCADORA | F1: UF | G1: BASE REGIONAL | H1: ÚLTIMO CONDUTOR | I1: CARGO | J1: GASTO ALUGUEL | K1: GASTO COMBUSTÍVEL FEVEREIRO | L1: GASTO COMBUSTÍVE MARÇO | M1: GASTO COMBUSTÍVE ABRIL | N1: GASTO TAGY | O1: VENCIMENTO CONTRATO | P1: OBSERVAÇÕES | Q1: VALOR LOCADORA | R1: AUDI. VALOR | S1: MÊS FIM | T1: ANO FIM | U1: STATUS | V1: C.CUSTO | W1: IC | X1: CLIENTE | Y1: GASTO COMBUTIVEL NO TRIMESTRE (JAN,FEV,MAR) | Z1: MÉDIA MÊS POR TRIMESTRE
A2: UAS3B92 | B2: =VLOOKUP(A2,UNIC!C:W,2,0) -> SAVEIRO | C2: =VLOOKUP(A2,UNIC!C:W,3,0) -> UTILITARIO | D2: =VLOOKUP(A2,UNIC!C:W,5,0) -> 2026 | E2: =VLOOKUP(A2,UNIC!C:W,21,0) -> MOVIDA | F2: =VLOOKUP(Tabela1[[#This Row],[PLACA]],UNIC!C:R,15,0) -> RS | G2: =VLOOKUP(Tabela1[[#This Row],[PLACA]],UNIC!C:R,16,0) -> SUL | H2: =VLOOKUP(A2,UNIC!C:H,6,0) -> - | I2: =VLOOKUP(H2,UNIC!H:J,3,0) -> - | J2: =VLOOKUP(Tabela1[[#This Row],[PLACA]],UNIC!C:V,20,0) -> R$ 0,00 | K2: =IFERROR(VALUE(VLOOKUP(Tabela1[[#This Row],[PLACA]],[1]Planilha2!$A:$F,3,0)),"") | L2: =IFERROR(VALUE(VLOOKUP(Tabela1[[#This Row],[PLACA]],[1]Planilha2!$A:$F,4,0)),"") | M2: =IFERROR(VALUE(VLOOKUP(Tabela1[[#This Row],[PLACA]],[1]Planilha2!$A:$F,5,0)),"") | O2: =VLOOKUP(Tabela1[[#This Row],[PLACA]],BASE_LOCADORAS!B:F,5,0) -> #N/A | P2: =IF(Tabela1[[#This Row],[VENCIMENTO CONTRATO]]="SEM DADOS", "SEM DADOS", IF(ISERROR(DATEDIF(TODAY(),Tabela1[[#This Row],[VENCIMENTO CONTRATO]],"d")), "VENCIDO", IF(DATEDIF(TODAY(),Tabela1[[#This Row],[VENCIMENTO CONTRATO]],"d")>90, "EM DIAS", "ATENÇÃO" ) ) ) -> #N/A | Q2: =VLOOKUP(Tabela1[[#This Row],[PLACA]],BASE_LOCADORAS!B:G,6,0) -> #N/A | R2: =Tabela1[[#This Row],[VALOR LOCADORA]]=Tabela1[[#This Row],[GASTO ALUGUEL]] -> #N/A | S2: =UPPER(TEXT(Tabela1[[#This Row],[VENCIMENTO CONTRATO]],"MMM")) -> #N/A | T2: =IFERROR(YEAR(Tabela1[[#This Row],[VENCIMENTO CONTRATO]]),"-") -> - | U2: =VLOOKUP(Tabela1[[#This Row],[PLACA]],UNIC!C:T,18,0) -> PATIO | V2: =SUBSTITUTE(VLOOKUP(Tabela1[[#This Row],[PLACA]],UNIC!C:K,9,0),".", "") | W2: =VLOOKUP(Tabela1[[#This Row],[PLACA]],UNIC!C:M,10,0) -> 0 | X2: =VLOOKUP(Tabela1[[#This Row],[PLACA]],UNIC!C:M,11,0) -> 0 | Y2: =SUM(Tabela1[[#This Row],[GASTO COMBUSTÍVEL FEVEREIRO]:[GASTO COMBUSTÍVE ABRIL]]) -> 0 | Z2: =IFERROR(AVERAGE(Tabela1[[#This Row],[GASTO COMBUSTÍVE ABRIL]:[GASTO COMBUSTÍVE MARÇO]]),"-") -> -
A3: UAS3I79 | B3: =VLOOKUP(A3,UNIC!C:W,2,0) -> SAVEIRO | C3: =VLOOKUP(A3,UNIC!C:W,3,0) -> UTILITARIO | D3: =VLOOKUP(A3,UNIC!C:W,5,0) -> 2026 | E3: =VLOOKUP(A3,UNIC!C:W,21,0) -> MOVIDA | F3: =VLOOKUP(Tabela1[[#This Row],[PLACA]],UNIC!C:R,15,0) -> RS | G3: =VLOOKUP(Tabela1[[#This Row],[PLACA]],UNIC!C:R,16,0) -> SUL | H3: =VLOOKUP(A3,UNIC!C:H,6,0) -> - | I3: =VLOOKUP(H3,UNIC!H:J,3,0) -> - | J3: =VLOOKUP(Tabela1[[#This Row],[PLACA]],UNIC!C:V,20,0) -> R$ 0,00 | K3: =IFERROR(VALUE(VLOOKUP(Tabela1[[#This Row],[PLACA]],[1]Planilha2!$A:$F,3,0)),"") | L3: =IFERROR(VALUE(VLOOKUP(Tabela1[[#This Row],[PLACA]],[1]Planilha2!$A:$F,4,0)),"") | M3: =IFERROR(VALUE(VLOOKUP(Tabela1[[#This Row],[PLACA]],[1]Planilha2!$A:$F,5,0)),"") | O3: =VLOOKUP(Tabela1[[#This Row],[PLACA]],BASE_LOCADORAS!B:F,5,0) -> #N/A | P3: =IF(Tabela1[[#This Row],[VENCIMENTO CONTRATO]]="SEM DADOS", "SEM DADOS", IF(ISERROR(DATEDIF(TODAY(),Tabela1[[#This Row],[VENCIMENTO CONTRATO]],"d")), "VENCIDO", IF(DATEDIF(TODAY(),Tabela1[[#This Row],[VENCIMENTO CONTRATO]],"d")>90, "EM DIAS", "ATENÇÃO" ) ) ) -> #N/A | Q3: =VLOOKUP(Tabela1[[#This Row],[PLACA]],BASE_LOCADORAS!B:G,6,0) -> #N/A | R3: =Tabela1[[#This Row],[VALOR LOCADORA]]=Tabela1[[#This Row],[GASTO ALUGUEL]] -> #N/A | S3: =UPPER(TEXT(Tabela1[[#This Row],[VENCIMENTO CONTRATO]],"MMM")) -> #N/A | T3: =IFERROR(YEAR(Tabela1[[#This Row],[VENCIMENTO CONTRATO]]),"-") -> - | U3: =VLOOKUP(Tabela1[[#This Row],[PLACA]],UNIC!C:T,18,0) -> PATIO | V3: =SUBSTITUTE(VLOOKUP(Tabela1[[#This Row],[PLACA]],UNIC!C:K,9,0),".", "") | W3: =VLOOKUP(Tabela1[[#This Row],[PLACA]],UNIC!C:M,10,0) -> 0 | X3: =VLOOKUP(Tabela1[[#This Row],[PLACA]],UNIC!C:M,11,0) -> 0 | Y3: =SUM(Tabela1[[#This Row],[GASTO COMBUSTÍVEL FEVEREIRO]:[GASTO COMBUSTÍVE ABRIL]]) -> 0 | Z3: =IFERROR(AVERAGE(Tabela1[[#This Row],[GASTO COMBUSTÍVE ABRIL]:[GASTO COMBUSTÍVE MARÇO]]),"-") -> -
A4: UAS2J80 | B4: =VLOOKUP(A4,UNIC!C:W,2,0) -> SAVEIRO | C4: =VLOOKUP(A4,UNIC!C:W,3,0) -> UTILITARIO | D4: =VLOOKUP(A4,UNIC!C:W,5,0) -> 2026 | E4: =VLOOKUP(A4,UNIC!C:W,21,0) -> MOVIDA | F4: =VLOOKUP(Tabela1[[#This Row],[PLACA]],UNIC!C:R,15,0) -> RS | G4: =VLOOKUP(Tabela1[[#This Row],[PLACA]],UNIC!C:R,16,0) -> SUL | H4: =VLOOKUP(A4,UNIC!C:H,6,0) -> - | I4: =VLOOKUP(H4,UNIC!H:J,3,0) -> - | J4: =VLOOKUP(Tabela1[[#This Row],[PLACA]],UNIC!C:V,20,0) -> R$ 0,00 | K4: =IFERROR(VALUE(VLOOKUP(Tabela1[[#This Row],[PLACA]],[1]Planilha2!$A:$F,3,0)),"") | L4: =IFERROR(VALUE(VLOOKUP(Tabela1[[#This Row],[PLACA]],[1]Planilha2!$A:$F,4,0)),"") | M4: =IFERROR(VALUE(VLOOKUP(Tabela1[[#This Row],[PLACA]],[1]Planilha2!$A:$F,5,0)),"") | O4: =VLOOKUP(Tabela1[[#This Row],[PLACA]],BASE_LOCADORAS!B:F,5,0) -> #N/A | P4: =IF(Tabela1[[#This Row],[VENCIMENTO CONTRATO]]="SEM DADOS", "SEM DADOS", IF(ISERROR(DATEDIF(TODAY(),Tabela1[[#This Row],[VENCIMENTO CONTRATO]],"d")), "VENCIDO", IF(DATEDIF(TODAY(),Tabela1[[#This Row],[VENCIMENTO CONTRATO]],"d")>90, "EM DIAS", "ATENÇÃO" ) ) ) -> #N/A | Q4: =VLOOKUP(Tabela1[[#This Row],[PLACA]],BASE_LOCADORAS!B:G,6,0) -> #N/A | R4: =Tabela1[[#This Row],[VALOR LOCADORA]]=Tabela1[[#This Row],[GASTO ALUGUEL]] -> #N/A | S4: =UPPER(TEXT(Tabela1[[#This Row],[VENCIMENTO CONTRATO]],"MMM")) -> #N/A | T4: =IFERROR(YEAR(Tabela1[[#This Row],[VENCIMENTO CONTRATO]]),"-") -> - | U4: =VLOOKUP(Tabela1[[#This Row],[PLACA]],UNIC!C:T,18,0) -> PATIO | V4: =SUBSTITUTE(VLOOKUP(Tabela1[[#This Row],[PLACA]],UNIC!C:K,9,0),".", "") | W4: =VLOOKUP(Tabela1[[#This Row],[PLACA]],UNIC!C:M,10,0) -> 0 | X4: =VLOOKUP(Tabela1[[#This Row],[PLACA]],UNIC!C:M,11,0) -> 0 | Y4: =SUM(Tabela1[[#This Row],[GASTO COMBUSTÍVEL FEVEREIRO]:[GASTO COMBUSTÍVE ABRIL]]) -> 0 | Z4: =IFERROR(AVERAGE(Tabela1[[#This Row],[GASTO COMBUSTÍVE ABRIL]:[GASTO COMBUSTÍVE MARÇO]]),"-") -> -
A5: UAS3E08 | B5: =VLOOKUP(A5,UNIC!C:W,2,0) -> SAVEIRO | C5: =VLOOKUP(A5,UNIC!C:W,3,0) -> UTILITARIO | D5: =VLOOKUP(A5,UNIC!C:W,5,0) -> 2026 | E5: =VLOOKUP(A5,UNIC!C:W,21,0) -> MOVIDA | F5: =VLOOKUP(Tabela1[[#This Row],[PLACA]],UNIC!C:R,15,0) -> RS | G5: =VLOOKUP(Tabela1[[#This Row],[PLACA]],UNIC!C:R,16,0) -> SUL | H5: =VLOOKUP(A5,UNIC!C:H,6,0) -> - | I5: =VLOOKUP(H5,UNIC!H:J,3,0) -> - | J5: =VLOOKUP(Tabela1[[#This Row],[PLACA]],UNIC!C:V,20,0) -> R$ 0,00 | K5: =IFERROR(VALUE(VLOOKUP(Tabela1[[#This Row],[PLACA]],[1]Planilha2!$A:$F,3,0)),"") | L5: =IFERROR(VALUE(VLOOKUP(Tabela1[[#This Row],[PLACA]],[1]Planilha2!$A:$F,4,0)),"") | M5: =IFERROR(VALUE(VLOOKUP(Tabela1[[#This Row],[PLACA]],[1]Planilha2!$A:$F,5,0)),"") | O5: =VLOOKUP(Tabela1[[#This Row],[PLACA]],BASE_LOCADORAS!B:F,5,0) -> #N/A | P5: =IF(Tabela1[[#This Row],[VENCIMENTO CONTRATO]]="SEM DADOS", "SEM DADOS", IF(ISERROR(DATEDIF(TODAY(),Tabela1[[#This Row],[VENCIMENTO CONTRATO]],"d")), "VENCIDO", IF(DATEDIF(TODAY(),Tabela1[[#This Row],[VENCIMENTO CONTRATO]],"d")>90, "EM DIAS", "ATENÇÃO" ) ) ) -> #N/A | Q5: =VLOOKUP(Tabela1[[#This Row],[PLACA]],BASE_LOCADORAS!B:G,6,0) -> #N/A | R5: =Tabela1[[#This Row],[VALOR LOCADORA]]=Tabela1[[#This Row],[GASTO ALUGUEL]] -> #N/A | S5: =UPPER(TEXT(Tabela1[[#This Row],[VENCIMENTO CONTRATO]],"MMM")) -> #N/A | T5: =IFERROR(YEAR(Tabela1[[#This Row],[VENCIMENTO CONTRATO]]),"-") -> - | U5: =VLOOKUP(Tabela1[[#This Row],[PLACA]],UNIC!C:T,18,0) -> PATIO | V5: =SUBSTITUTE(VLOOKUP(Tabela1[[#This Row],[PLACA]],UNIC!C:K,9,0),".", "") | W5: =VLOOKUP(Tabela1[[#This Row],[PLACA]],UNIC!C:M,10,0) -> 0 | X5: =VLOOKUP(Tabela1[[#This Row],[PLACA]],UNIC!C:M,11,0) -> 0 | Y5: =SUM(Tabela1[[#This Row],[GASTO COMBUSTÍVEL FEVEREIRO]:[GASTO COMBUSTÍVE ABRIL]]) -> 0 | Z5: =IFERROR(AVERAGE(Tabela1[[#This Row],[GASTO COMBUSTÍVE ABRIL]:[GASTO COMBUSTÍVE MARÇO]]),"-") -> -
A6: UAS3G94 | B6: =VLOOKUP(A6,UNIC!C:W,2,0) -> SAVEIRO | C6: =VLOOKUP(A6,UNIC!C:W,3,0) -> UTILITARIO | D6: =VLOOKUP(A6,UNIC!C:W,5,0) -> 2026 | E6: =VLOOKUP(A6,UNIC!C:W,21,0) -> MOVIDA | F6: =VLOOKUP(Tabela1[[#This Row],[PLACA]],UNIC!C:R,15,0) -> RS | G6: =VLOOKUP(Tabela1[[#This Row],[PLACA]],UNIC!C:R,16,0) -> SUL | H6: =VLOOKUP(A6,UNIC!C:H,6,0) -> - | I6: =VLOOKUP(H6,UNIC!H:J,3,0) -> - | J6: =VLOOKUP(Tabela1[[#This Row],[PLACA]],UNIC!C:V,20,0) -> R$ 0,00 | K6: =IFERROR(VALUE(VLOOKUP(Tabela1[[#This Row],[PLACA]],[1]Planilha2!$A:$F,3,0)),"") | L6: =IFERROR(VALUE(VLOOKUP(Tabela1[[#This Row],[PLACA]],[1]Planilha2!$A:$F,4,0)),"") | M6: =IFERROR(VALUE(VLOOKUP(Tabela1[[#This Row],[PLACA]],[1]Planilha2!$A:$F,5,0)),"") | O6: =VLOOKUP(Tabela1[[#This Row],[PLACA]],BASE_LOCADORAS!B:F,5,0) -> #N/A | P6: =IF(Tabela1[[#This Row],[VENCIMENTO CONTRATO]]="SEM DADOS", "SEM DADOS", IF(ISERROR(DATEDIF(TODAY(),Tabela1[[#This Row],[VENCIMENTO CONTRATO]],"d")), "VENCIDO", IF(DATEDIF(TODAY(),Tabela1[[#This Row],[VENCIMENTO CONTRATO]],"d")>90, "EM DIAS", "ATENÇÃO" ) ) ) -> #N/A | Q6: =VLOOKUP(Tabela1[[#This Row],[PLACA]],BASE_LOCADORAS!B:G,6,0) -> #N/A | R6: =Tabela1[[#This Row],[VALOR LOCADORA]]=Tabela1[[#This Row],[GASTO ALUGUEL]] -> #N/A | S6: =UPPER(TEXT(Tabela1[[#This Row],[VENCIMENTO CONTRATO]],"MMM")) -> #N/A | T6: =IFERROR(YEAR(Tabela1[[#This Row],[VENCIMENTO CONTRATO]]),"-") -> - | U6: =VLOOKUP(Tabela1[[#This Row],[PLACA]],UNIC!C:T,18,0) -> PATIO | V6: =SUBSTITUTE(VLOOKUP(Tabela1[[#This Row],[PLACA]],UNIC!C:K,9,0),".", "") | W6: =VLOOKUP(Tabela1[[#This Row],[PLACA]],UNIC!C:M,10,0) -> 0 | X6: =VLOOKUP(Tabela1[[#This Row],[PLACA]],UNIC!C:M,11,0) -> 0 | Y6: =SUM(Tabela1[[#This Row],[GASTO COMBUSTÍVEL FEVEREIRO]:[GASTO COMBUSTÍVE ABRIL]]) -> 0 | Z6: =IFERROR(AVERAGE(Tabela1[[#This Row],[GASTO COMBUSTÍVE ABRIL]:[GASTO COMBUSTÍVE MARÇO]]),"-") -> -
A7: UAS0H69 | B7: =VLOOKUP(A7,UNIC!C:W,2,0) -> SAVEIRO | C7: =VLOOKUP(A7,UNIC!C:W,3,0) -> UTILITARIO | D7: =VLOOKUP(A7,UNIC!C:W,5,0) -> 2026 | E7: =VLOOKUP(A7,UNIC!C:W,21,0) -> MOVIDA | F7: =VLOOKUP(Tabela1[[#This Row],[PLACA]],UNIC!C:R,15,0) -> RS | G7: =VLOOKUP(Tabela1[[#This Row],[PLACA]],UNIC!C:R,16,0) -> SUL | H7: =VLOOKUP(A7,UNIC!C:H,6,0) -> - | I7: =VLOOKUP(H7,UNIC!H:J,3,0) -> - | J7: =VLOOKUP(Tabela1[[#This Row],[PLACA]],UNIC!C:V,20,0) -> R$ 0,00 | K7: =IFERROR(VALUE(VLOOKUP(Tabela1[[#This Row],[PLACA]],[1]Planilha2!$A:$F,3,0)),"") | L7: =IFERROR(VALUE(VLOOKUP(Tabela1[[#This Row],[PLACA]],[1]Planilha2!$A:$F,4,0)),"") | M7: =IFERROR(VALUE(VLOOKUP(Tabela1[[#This Row],[PLACA]],[1]Planilha2!$A:$F,5,0)),"") | O7: =VLOOKUP(Tabela1[[#This Row],[PLACA]],BASE_LOCADORAS!B:F,5,0) -> #N/A | P7: =IF(Tabela1[[#This Row],[VENCIMENTO CONTRATO]]="SEM DADOS", "SEM DADOS", IF(ISERROR(DATEDIF(TODAY(),Tabela1[[#This Row],[VENCIMENTO CONTRATO]],"d")), "VENCIDO", IF(DATEDIF(TODAY(),Tabela1[[#This Row],[VENCIMENTO CONTRATO]],"d")>90, "EM DIAS", "ATENÇÃO" ) ) ) -> #N/A | Q7: =VLOOKUP(Tabela1[[#This Row],[PLACA]],BASE_LOCADORAS!B:G,6,0) -> #N/A | R7: =Tabela1[[#This Row],[VALOR LOCADORA]]=Tabela1[[#This Row],[GASTO ALUGUEL]] -> #N/A | S7: =UPPER(TEXT(Tabela1[[#This Row],[VENCIMENTO CONTRATO]],"MMM")) -> #N/A | T7: =IFERROR(YEAR(Tabela1[[#This Row],[VENCIMENTO CONTRATO]]),"-") -> - | U7: =VLOOKUP(Tabela1[[#This Row],[PLACA]],UNIC!C:T,18,0) -> PATIO | V7: =SUBSTITUTE(VLOOKUP(Tabela1[[#This Row],[PLACA]],UNIC!C:K,9,0),".", "") | W7: =VLOOKUP(Tabela1[[#This Row],[PLACA]],UNIC!C:M,10,0) -> 0 | X7: =VLOOKUP(Tabela1[[#This Row],[PLACA]],UNIC!C:M,11,0) -> 0 | Y7: =SUM(Tabela1[[#This Row],[GASTO COMBUSTÍVEL FEVEREIRO]:[GASTO COMBUSTÍVE ABRIL]]) -> 0 | Z7: =IFERROR(AVERAGE(Tabela1[[#This Row],[GASTO COMBUSTÍVE ABRIL]:[GASTO COMBUSTÍVE MARÇO]]),"-") -> -
A8: UAS0H57 | B8: =VLOOKUP(A8,UNIC!C:W,2,0) -> SAVEIRO | C8: =VLOOKUP(A8,UNIC!C:W,3,0) -> UTILITARIO | D8: =VLOOKUP(A8,UNIC!C:W,5,0) -> 2026 | E8: =VLOOKUP(A8,UNIC!C:W,21,0) -> MOVIDA | F8: =VLOOKUP(Tabela1[[#This Row],[PLACA]],UNIC!C:R,15,0) -> RS | G8: =VLOOKUP(Tabela1[[#This Row],[PLACA]],UNIC!C:R,16,0) -> SUL | H8: =VLOOKUP(A8,UNIC!C:H,6,0) -> - | I8: =VLOOKUP(H8,UNIC!H:J,3,0) -> - | J8: =VLOOKUP(Tabela1[[#This Row],[PLACA]],UNIC!C:V,20,0) -> R$ 0,00 | K8: =IFERROR(VALUE(VLOOKUP(Tabela1[[#This Row],[PLACA]],[1]Planilha2!$A:$F,3,0)),"") | L8: =IFERROR(VALUE(VLOOKUP(Tabela1[[#This Row],[PLACA]],[1]Planilha2!$A:$F,4,0)),"") | M8: =IFERROR(VALUE(VLOOKUP(Tabela1[[#This Row],[PLACA]],[1]Planilha2!$A:$F,5,0)),"") | O8: =VLOOKUP(Tabela1[[#This Row],[PLACA]],BASE_LOCADORAS!B:F,5,0) -> #N/A | P8: =IF(Tabela1[[#This Row],[VENCIMENTO CONTRATO]]="SEM DADOS", "SEM DADOS", IF(ISERROR(DATEDIF(TODAY(),Tabela1[[#This Row],[VENCIMENTO CONTRATO]],"d")), "VENCIDO", IF(DATEDIF(TODAY(),Tabela1[[#This Row],[VENCIMENTO CONTRATO]],"d")>90, "EM DIAS", "ATENÇÃO" ) ) ) -> #N/A | Q8: =VLOOKUP(Tabela1[[#This Row],[PLACA]],BASE_LOCADORAS!B:G,6,0) -> #N/A | R8: =Tabela1[[#This Row],[VALOR LOCADORA]]=Tabela1[[#This Row],[GASTO ALUGUEL]] -> #N/A | S8: =UPPER(TEXT(Tabela1[[#This Row],[VENCIMENTO CONTRATO]],"MMM")) -> #N/A | T8: =IFERROR(YEAR(Tabela1[[#This Row],[VENCIMENTO CONTRATO]]),"-") -> - | U8: =VLOOKUP(Tabela1[[#This Row],[PLACA]],UNIC!C:T,18,0) -> PATIO | V8: =SUBSTITUTE(VLOOKUP(Tabela1[[#This Row],[PLACA]],UNIC!C:K,9,0),".", "") | W8: =VLOOKUP(Tabela1[[#This Row],[PLACA]],UNIC!C:M,10,0) -> 0 | X8: =VLOOKUP(Tabela1[[#This Row],[PLACA]],UNIC!C:M,11,0) -> 0 | Y8: =SUM(Tabela1[[#This Row],[GASTO COMBUSTÍVEL FEVEREIRO]:[GASTO COMBUSTÍVE ABRIL]]) -> 0 | Z8: =IFERROR(AVERAGE(Tabela1[[#This Row],[GASTO COMBUSTÍVE ABRIL]:[GASTO COMBUSTÍVE MARÇO]]),"-") -> -
A9: UAS0H48 | B9: =VLOOKUP(A9,UNIC!C:W,2,0) -> SAVEIRO | C9: =VLOOKUP(A9,UNIC!C:W,3,0) -> UTILITARIO | D9: =VLOOKUP(A9,UNIC!C:W,5,0) -> 2026 | E9: =VLOOKUP(A9,UNIC!C:W,21,0) -> MOVIDA | F9: =VLOOKUP(Tabela1[[#This Row],[PLACA]],UNIC!C:R,15,0) -> RS | G9: =VLOOKUP(Tabela1[[#This Row],[PLACA]],UNIC!C:R,16,0) -> SUL | H9: =VLOOKUP(A9,UNIC!C:H,6,0) -> - | I9: =VLOOKUP(H9,UNIC!H:J,3,0) -> - | J9: =VLOOKUP(Tabela1[[#This Row],[PLACA]],UNIC!C:V,20,0) -> R$ 0,00 | K9: =IFERROR(VALUE(VLOOKUP(Tabela1[[#This Row],[PLACA]],[1]Planilha2!$A:$F,3,0)),"") | L9: =IFERROR(VALUE(VLOOKUP(Tabela1[[#This Row],[PLACA]],[1]Planilha2!$A:$F,4,0)),"") | M9: =IFERROR(VALUE(VLOOKUP(Tabela1[[#This Row],[PLACA]],[1]Planilha2!$A:$F,5,0)),"") | O9: =VLOOKUP(Tabela1[[#This Row],[PLACA]],BASE_LOCADORAS!B:F,5,0) -> #N/A | P9: =IF(Tabela1[[#This Row],[VENCIMENTO CONTRATO]]="SEM DADOS", "SEM DADOS", IF(ISERROR(DATEDIF(TODAY(),Tabela1[[#This Row],[VENCIMENTO CONTRATO]],"d")), "VENCIDO", IF(DATEDIF(TODAY(),Tabela1[[#This Row],[VENCIMENTO CONTRATO]],"d")>90, "EM DIAS", "ATENÇÃO" ) ) ) -> #N/A | Q9: =VLOOKUP(Tabela1[[#This Row],[PLACA]],BASE_LOCADORAS!B:G,6,0) -> #N/A | R9: =Tabela1[[#This Row],[VALOR LOCADORA]]=Tabela1[[#This Row],[GASTO ALUGUEL]] -> #N/A | S9: =UPPER(TEXT(Tabela1[[#This Row],[VENCIMENTO CONTRATO]],"MMM")) -> #N/A | T9: =IFERROR(YEAR(Tabela1[[#This Row],[VENCIMENTO CONTRATO]]),"-") -> - | U9: =VLOOKUP(Tabela1[[#This Row],[PLACA]],UNIC!C:T,18,0) -> PATIO | V9: =SUBSTITUTE(VLOOKUP(Tabela1[[#This Row],[PLACA]],UNIC!C:K,9,0),".", "") | W9: =VLOOKUP(Tabela1[[#This Row],[PLACA]],UNIC!C:M,10,0) -> 0 | X9: =VLOOKUP(Tabela1[[#This Row],[PLACA]],UNIC!C:M,11,0) -> 0 | Y9: =SUM(Tabela1[[#This Row],[GASTO COMBUSTÍVEL FEVEREIRO]:[GASTO COMBUSTÍVE ABRIL]]) -> 0 | Z9: =IFERROR(AVERAGE(Tabela1[[#This Row],[GASTO COMBUSTÍVE ABRIL]:[GASTO COMBUSTÍVE MARÇO]]),"-") -> -
A10: UAS0H36 | B10: =VLOOKUP(A10,UNIC!C:W,2,0) -> SAVEIRO | C10: =VLOOKUP(A10,UNIC!C:W,3,0) -> UTILITARIO | D10: =VLOOKUP(A10,UNIC!C:W,5,0) -> 2026 | E10: =VLOOKUP(A10,UNIC!C:W,21,0) -> MOVIDA | F10: =VLOOKUP(Tabela1[[#This Row],[PLACA]],UNIC!C:R,15,0) -> RS | G10: =VLOOKUP(Tabela1[[#This Row],[PLACA]],UNIC!C:R,16,0) -> SUL | H10: =VLOOKUP(A10,UNIC!C:H,6,0) -> - | I10: =VLOOKUP(H10,UNIC!H:J,3,0) -> - | J10: =VLOOKUP(Tabela1[[#This Row],[PLACA]],UNIC!C:V,20,0) -> R$ 2.026,00 | K10: =IFERROR(VALUE(VLOOKUP(Tabela1[[#This Row],[PLACA]],[1]Planilha2!$A:$F,3,0)),"") | L10: =IFERROR(VALUE(VLOOKUP(Tabela1[[#This Row],[PLACA]],[1]Planilha2!$A:$F,4,0)),"") | M10: =IFERROR(VALUE(VLOOKUP(Tabela1[[#This Row],[PLACA]],[1]Planilha2!$A:$F,5,0)),"") | O10: =VLOOKUP(Tabela1[[#This Row],[PLACA]],BASE_LOCADORAS!B:F,5,0) -> #N/A | P10: =IF(Tabela1[[#This Row],[VENCIMENTO CONTRATO]]="SEM DADOS", "SEM DADOS", IF(ISERROR(DATEDIF(TODAY(),Tabela1[[#This Row],[VENCIMENTO CONTRATO]],"d")), "VENCIDO", IF(DATEDIF(TODAY(),Tabela1[[#This Row],[VENCIMENTO CONTRATO]],"d")>90, "EM DIAS", "ATENÇÃO" ) ) ) -> #N/A | Q10: =VLOOKUP(Tabela1[[#This Row],[PLACA]],BASE_LOCADORAS!B:G,6,0) -> #N/A | R10: =Tabela1[[#This Row],[VALOR LOCADORA]]=Tabela1[[#This Row],[GASTO ALUGUEL]] -> #N/A | S10: =UPPER(TEXT(Tabela1[[#This Row],[VENCIMENTO CONTRATO]],"MMM")) -> #N/A | T10: =IFERROR(YEAR(Tabela1[[#This Row],[VENCIMENTO CONTRATO]]),"-") -> - | U10: =VLOOKUP(Tabela1[[#This Row],[PLACA]],UNIC!C:T,18,0) -> PATIO | V10: =SUBSTITUTE(VLOOKUP(Tabela1[[#This Row],[PLACA]],UNIC!C:K,9,0),".", "") | W10: =VLOOKUP(Tabela1[[#This Row],[PLACA]],UNIC!C:M,10,0) -> 0 | X10: =VLOOKUP(Tabela1[[#This Row],[PLACA]],UNIC!C:M,11,0) -> 0 | Y10: =SUM(Tabela1[[#This Row],[GASTO COMBUSTÍVEL FEVEREIRO]:[GASTO COMBUSTÍVE ABRIL]]) -> 0 | Z10: =IFERROR(AVERAGE(Tabela1[[#This Row],[GASTO COMBUSTÍVE ABRIL]:[GASTO COMBUSTÍVE MARÇO]]),"-") -> -
A11: UAS0H21 | B11: =VLOOKUP(A11,UNIC!C:W,2,0) -> SAVEIRO | C11: =VLOOKUP(A11,UNIC!C:W,3,0) -> UTILITARIO | D11: =VLOOKUP(A11,UNIC!C:W,5,0) -> 2026 | E11: =VLOOKUP(A11,UNIC!C:W,21,0) -> MOVIDA | F11: =VLOOKUP(Tabela1[[#This Row],[PLACA]],UNIC!C:R,15,0) -> RS | G11: =VLOOKUP(Tabela1[[#This Row],[PLACA]],UNIC!C:R,16,0) -> SUL | H11: =VLOOKUP(A11,UNIC!C:H,6,0) -> - | I11: =VLOOKUP(H11,UNIC!H:J,3,0) -> - | J11: =VLOOKUP(Tabela1[[#This Row],[PLACA]],UNIC!C:V,20,0) -> R$ 0,00 | K11: =IFERROR(VALUE(VLOOKUP(Tabela1[[#This Row],[PLACA]],[1]Planilha2!$A:$F,3,0)),"") | L11: =IFERROR(VALUE(VLOOKUP(Tabela1[[#This Row],[PLACA]],[1]Planilha2!$A:$F,4,0)),"") | M11: =IFERROR(VALUE(VLOOKUP(Tabela1[[#This Row],[PLACA]],[1]Planilha2!$A:$F,5,0)),"") | O11: =VLOOKUP(Tabela1[[#This Row],[PLACA]],BASE_LOCADORAS!B:F,5,0) -> #N/A | P11: =IF(Tabela1[[#This Row],[VENCIMENTO CONTRATO]]="SEM DADOS", "SEM DADOS", IF(ISERROR(DATEDIF(TODAY(),Tabela1[[#This Row],[VENCIMENTO CONTRATO]],"d")), "VENCIDO", IF(DATEDIF(TODAY(),Tabela1[[#This Row],[VENCIMENTO CONTRATO]],"d")>90, "EM DIAS", "ATENÇÃO" ) ) ) -> #N/A | Q11: =VLOOKUP(Tabela1[[#This Row],[PLACA]],BASE_LOCADORAS!B:G,6,0) -> #N/A | R11: =Tabela1[[#This Row],[VALOR LOCADORA]]=Tabela1[[#This Row],[GASTO ALUGUEL]] -> #N/A | S11: =UPPER(TEXT(Tabela1[[#This Row],[VENCIMENTO CONTRATO]],"MMM")) -> #N/A | T11: =IFERROR(YEAR(Tabela1[[#This Row],[VENCIMENTO CONTRATO]]),"-") -> - | U11: =VLOOKUP(Tabela1[[#This Row],[PLACA]],UNIC!C:T,18,0) -> PATIO | V11: =SUBSTITUTE(VLOOKUP(Tabela1[[#This Row],[PLACA]],UNIC!C:K,9,0),".", "") | W11: =VLOOKUP(Tabela1[[#This Row],[PLACA]],UNIC!C:M,10,0) -> 0 | X11: =VLOOKUP(Tabela1[[#This Row],[PLACA]],UNIC!C:M,11,0) -> 0 | Y11: =SUM(Tabela1[[#This Row],[GASTO COMBUSTÍVEL FEVEREIRO]:[GASTO COMBUSTÍVE ABRIL]]) -> 0 | Z11: =IFERROR(AVERAGE(Tabela1[[#This Row],[GASTO COMBUSTÍVE ABRIL]:[GASTO COMBUSTÍVE MARÇO]]),"-") -> -
A12: UAS0G99 | B12: =VLOOKUP(A12,UNIC!C:W,2,0) -> SAVEIRO | C12: =VLOOKUP(A12,UNIC!C:W,3,0) -> UTILITARIO | D12: =VLOOKUP(A12,UNIC!C:W,5,0) -> 2026 | E12: =VLOOKUP(A12,UNIC!C:W,21,0) -> MOVIDA | F12: =VLOOKUP(Tabela1[[#This Row],[PLACA]],UNIC!C:R,15,0) -> RS | G12: =VLOOKUP(Tabela1[[#This Row],[PLACA]],UNIC!C:R,16,0) -> SUL | H12: =VLOOKUP(A12,UNIC!C:H,6,0) -> - | I12: =VLOOKUP(H12,UNIC!H:J,3,0) -> - | J12: =VLOOKUP(Tabela1[[#This Row],[PLACA]],UNIC!C:V,20,0) -> R$ 0,00 | K12: =IFERROR(VALUE(VLOOKUP(Tabela1[[#This Row],[PLACA]],[1]Planilha2!$A:$F,3,0)),"") | L12: =IFERROR(VALUE(VLOOKUP(Tabela1[[#This Row],[PLACA]],[1]Planilha2!$A:$F,4,0)),"") | M12: =IFERROR(VALUE(VLOOKUP(Tabela1[[#This Row],[PLACA]],[1]Planilha2!$A:$F,5,0)),"") | O12: =VLOOKUP(Tabela1[[#This Row],[PLACA]],BASE_LOCADORAS!B:F,5,0) -> #N/A | P12: =IF(Tabela1[[#This Row],[VENCIMENTO CONTRATO]]="SEM DADOS", "SEM DADOS", IF(ISERROR(DATEDIF(TODAY(),Tabela1[[#This Row],[VENCIMENTO CONTRATO]],"d")), "VENCIDO", IF(DATEDIF(TODAY(),Tabela1[[#This Row],[VENCIMENTO CONTRATO]],"d")>90, "EM DIAS", "ATENÇÃO" ) ) ) -> #N/A | Q12: =VLOOKUP(Tabela1[[#This Row],[PLACA]],BASE_LOCADORAS!B:G,6,0) -> #N/A | R12: =Tabela1[[#This Row],[VALOR LOCADORA]]=Tabela1[[#This Row],[GASTO ALUGUEL]] -> #N/A | S12: =UPPER(TEXT(Tabela1[[#This Row],[VENCIMENTO CONTRATO]],"MMM")) -> #N/A | T12: =IFERROR(YEAR(Tabela1[[#This Row],[VENCIMENTO CONTRATO]]),"-") -> - | U12: =VLOOKUP(Tabela1[[#This Row],[PLACA]],UNIC!C:T,18,0) -> PATIO | V12: =SUBSTITUTE(VLOOKUP(Tabela1[[#This Row],[PLACA]],UNIC!C:K,9,0),".", "") | W12: =VLOOKUP(Tabela1[[#This Row],[PLACA]],UNIC!C:M,10,0) -> 0 | X12: =VLOOKUP(Tabela1[[#This Row],[PLACA]],UNIC!C:M,11,0) -> 0 | Y12: =SUM(Tabela1[[#This Row],[GASTO COMBUSTÍVEL FEVEREIRO]:[GASTO COMBUSTÍVE ABRIL]]) -> 0 | Z12: =IFERROR(AVERAGE(Tabela1[[#This Row],[GASTO COMBUSTÍVE ABRIL]:[GASTO COMBUSTÍVE MARÇO]]),"-") -> -
A13: UAS0G93 | B13: =VLOOKUP(A13,UNIC!C:W,2,0) -> SAVEIRO | C13: =VLOOKUP(A13,UNIC!C:W,3,0) -> UTILITARIO | D13: =VLOOKUP(A13,UNIC!C:W,5,0) -> 2026 | E13: =VLOOKUP(A13,UNIC!C:W,21,0) -> MOVIDA | F13: =VLOOKUP(Tabela1[[#This Row],[PLACA]],UNIC!C:R,15,0) -> RS | G13: =VLOOKUP(Tabela1[[#This Row],[PLACA]],UNIC!C:R,16,0) -> SUL | H13: =VLOOKUP(A13,UNIC!C:H,6,0) -> - | I13: =VLOOKUP(H13,UNIC!H:J,3,0) -> - | J13: =VLOOKUP(Tabela1[[#This Row],[PLACA]],UNIC!C:V,20,0) -> R$ 0,00 | K13: =IFERROR(VALUE(VLOOKUP(Tabela1[[#This Row],[PLACA]],[1]Planilha2!$A:$F,3,0)),"") | L13: =IFERROR(VALUE(VLOOKUP(Tabela1[[#This Row],[PLACA]],[1]Planilha2!$A:$F,4,0)),"") | M13: =IFERROR(VALUE(VLOOKUP(Tabela1[[#This Row],[PLACA]],[1]Planilha2!$A:$F,5,0)),"") | O13: =VLOOKUP(Tabela1[[#This Row],[PLACA]],BASE_LOCADORAS!B:F,5,0) -> #N/A | P13: =IF(Tabela1[[#This Row],[VENCIMENTO CONTRATO]]="SEM DADOS", "SEM DADOS", IF(ISERROR(DATEDIF(TODAY(),Tabela1[[#This Row],[VENCIMENTO CONTRATO]],"d")), "VENCIDO", IF(DATEDIF(TODAY(),Tabela1[[#This Row],[VENCIMENTO CONTRATO]],"d")>90, "EM DIAS", "ATENÇÃO" ) ) ) -> #N/A | Q13: =VLOOKUP(Tabela1[[#This Row],[PLACA]],BASE_LOCADORAS!B:G,6,0) -> #N/A | R13: =Tabela1[[#This Row],[VALOR LOCADORA]]=Tabela1[[#This Row],[GASTO ALUGUEL]] -> #N/A | S13: =UPPER(TEXT(Tabela1[[#This Row],[VENCIMENTO CONTRATO]],"MMM")) -> #N/A | T13: =IFERROR(YEAR(Tabela1[[#This Row],[VENCIMENTO CONTRATO]]),"-") -> - | U13: =VLOOKUP(Tabela1[[#This Row],[PLACA]],UNIC!C:T,18,0) -> PATIO | V13: =SUBSTITUTE(VLOOKUP(Tabela1[[#This Row],[PLACA]],UNIC!C:K,9,0),".", "") | W13: =VLOOKUP(Tabela1[[#This Row],[PLACA]],UNIC!C:M,10,0) -> 0 | X13: =VLOOKUP(Tabela1[[#This Row],[PLACA]],UNIC!C:M,11,0) -> 0 | Y13: =SUM(Tabela1[[#This Row],[GASTO COMBUSTÍVEL FEVEREIRO]:[GASTO COMBUSTÍVE ABRIL]]) -> 0 | Z13: =IFERROR(AVERAGE(Tabela1[[#This Row],[GASTO COMBUSTÍVE ABRIL]:[GASTO COMBUSTÍVE MARÇO]]),"-") -> -
... A137: CUE8J13 | B137: =VLOOKUP(A137,UNIC!C:W,2,0) -> SAVEIRO | C137: =VLOOKUP(A137,UNIC!C:W,3,0) -> UTILITARIO | D137: =VLOOKUP(A137,UNIC!C:W,5,0) -> 2026 | E137: =VLOOKUP(A137,UNIC!C:W,21,0) -> MOVIDA | F137: =VLOOKUP(Tabela1[[#This Row],[PLACA]],UNIC!C:R,15,0) -> GO | G137: =VLOOKUP(Tabela1[[#This Row],[PLACA]],UNIC!C:R,16,0) -> CENTRO OESTE | H137: =VLOOKUP(A137,UNIC!C:H,6,0) -> WAGNER TELLES DA SILVA | I137: =VLOOKUP(H137,UNIC!H:J,3,0) -> TECNICO DE MANUTENCAO PI I | J137: =VLOOKUP(Tabela1[[#This Row],[PLACA]],UNIC!C:V,20,0) -> R$ 1,00 | K137: =IFERROR(VALUE(VLOOKUP(Tabela1[[#This Row],[PLACA]],[1]Planilha2!$A:$F,3,0)),"") -> 0 | L137: =IFERROR(VALUE(VLOOKUP(Tabela1[[#This Row],[PLACA]],[1]Planilha2!$A:$F,4,0)),"") -> 0 | M137: =IFERROR(VALUE(VLOOKUP(Tabela1[[#This Row],[PLACA]],[1]Planilha2!$A:$F,5,0)),"") -> 1388.82 | O137: =VLOOKUP(Tabela1[[#This Row],[PLACA]],BASE_LOCADORAS!B:F,5,0) -> #N/A | P137: =IF(Tabela1[[#This Row],[VENCIMENTO CONTRATO]]="SEM DADOS", "SEM DADOS", IF(ISERROR(DATEDIF(TODAY(),Tabela1[[#This Row],[VENCIMENTO CONTRATO]],"d")), "VENCIDO", IF(DATEDIF(TODAY(),Tabela1[[#This Row],[VENCIMENTO CONTRATO]],"d")>90, "EM DIAS", "ATENÇÃO" ) ) ) -> #N/A | Q137: =VLOOKUP(Tabela1[[#This Row],[PLACA]],BASE_LOCADORAS!B:G,6,0) -> #N/A | R137: =Tabela1[[#This Row],[VALOR LOCADORA]]=Tabela1[[#This Row],[GASTO ALUGUEL]] -> #N/A | S137: =UPPER(TEXT(Tabela1[[#This Row],[VENCIMENTO CONTRATO]],"MMM")) -> #N/A | T137: =IFERROR(YEAR(Tabela1[[#This Row],[VENCIMENTO CONTRATO]]),"-") -> - | U137: =VLOOKUP(Tabela1[[#This Row],[PLACA]],UNIC!C:T,18,0) -> ATIVO | V137: =SUBSTITUTE(VLOOKUP(Tabela1[[#This Row],[PLACA]],UNIC!C:K,9,0),".", "") -> 12081 | W137: =VLOOKUP(Tabela1[[#This Row],[PLACA]],UNIC!C:M,10,0) -> 19019 | X137: =VLOOKUP(Tabela1[[#This Row],[PLACA]],UNIC!C:M,11,0) -> TIM MOVEL | Y137: =SUM(Tabela1[[#This Row],[GASTO COMBUSTÍVEL FEVEREIRO]:[GASTO COMBUSTÍVE ABRIL]]) -> 1388.82 | Z137: =IFERROR(AVERAGE(Tabela1[[#This Row],[GASTO COMBUSTÍVE ABRIL]:[GASTO COMBUSTÍVE MARÇO]]),"-") -> 694.41
A138: SGO5E22 | B138: =VLOOKUP(A138,UNIC!C:W,2,0) -> TRACKER | C138: =VLOOKUP(A138,UNIC!C:W,3,0) -> SUV | D138: =VLOOKUP(A138,UNIC!C:W,5,0) -> 2022 | E138: =VLOOKUP(A138,UNIC!C:W,21,0) -> PARTICULAR | F138: =VLOOKUP(Tabela1[[#This Row],[PLACA]],UNIC!C:R,15,0) -> DF | G138: =VLOOKUP(Tabela1[[#This Row],[PLACA]],UNIC!C:R,16,0) -> CENTRO OESTE | H138: CLEITON DOS SANTOS DIAS MAIA | I138: =VLOOKUP(H138,UNIC!H:J,3,0) -> GERENTE OPERACAO JR | J138: =VLOOKUP(Tabela1[[#This Row],[PLACA]],UNIC!C:V,20,0) -> R$ 2.000,00 | K138: =IFERROR(VALUE(VLOOKUP(Tabela1[[#This Row],[PLACA]],[1]Planilha2!$A:$F,3,0)),"") -> 0 | L138: =IFERROR(VALUE(VLOOKUP(Tabela1[[#This Row],[PLACA]],[1]Planilha2!$A:$F,4,0)),"") -> 845.12 | M138: =IFERROR(VALUE(VLOOKUP(Tabela1[[#This Row],[PLACA]],[1]Planilha2!$A:$F,5,0)),"") -> 980 | O138: =VLOOKUP(Tabela1[[#This Row],[PLACA]],BASE_LOCADORAS!B:F,5,0) -> #N/A | P138: =IF(Tabela1[[#This Row],[VENCIMENTO CONTRATO]]="SEM DADOS", "SEM DADOS", IF(ISERROR(DATEDIF(TODAY(),Tabela1[[#This Row],[VENCIMENTO CONTRATO]],"d")), "VENCIDO", IF(DATEDIF(TODAY(),Tabela1[[#This Row],[VENCIMENTO CONTRATO]],"d")>90, "EM DIAS", "ATENÇÃO" ) ) ) -> #N/A | Q138: =VLOOKUP(Tabela1[[#This Row],[PLACA]],BASE_LOCADORAS!B:G,6,0) -> #N/A | R138: =Tabela1[[#This Row],[VALOR LOCADORA]]=Tabela1[[#This Row],[GASTO ALUGUEL]] -> #N/A | S138: =UPPER(TEXT(Tabela1[[#This Row],[VENCIMENTO CONTRATO]],"MMM")) -> #N/A | T138: =IFERROR(YEAR(Tabela1[[#This Row],[VENCIMENTO CONTRATO]]),"-") -> - | U138: =VLOOKUP(Tabela1[[#This Row],[PLACA]],UNIC!C:T,18,0) -> PATIO | V138: =SUBSTITUTE(VLOOKUP(Tabela1[[#This Row],[PLACA]],UNIC!C:K,9,0),".", "") | W138: =VLOOKUP(Tabela1[[#This Row],[PLACA]],UNIC!C:M,10,0) -> 0 | X138: =VLOOKUP(Tabela1[[#This Row],[PLACA]],UNIC!C:M,11,0) -> 0 | Y138: =SUM(Tabela1[[#This Row],[GASTO COMBUSTÍVEL FEVEREIRO]:[GASTO COMBUSTÍVE ABRIL]]) -> 1825.12 | Z138: =IFERROR(AVERAGE(Tabela1[[#This Row],[GASTO COMBUSTÍVE ABRIL]:[GASTO COMBUSTÍVE MARÇO]]),"-") -> 912.56
A139: LMY9J53 | B139: =VLOOKUP(A139,UNIC!C:W,2,0) -> VW | C139: =VLOOKUP(A139,UNIC!C:W,3,0) -> LEVE | D139: =VLOOKUP(A139,UNIC!C:W,5,0) -> 2020 | E139: =VLOOKUP(A139,UNIC!C:W,21,0) -> PARTICULAR | F139: =VLOOKUP(Tabela1[[#This Row],[PLACA]],UNIC!C:R,15,0) -> ES | G139: =VLOOKUP(Tabela1[[#This Row],[PLACA]],UNIC!C:R,16,0) -> SUDESTE | H139: =VLOOKUP(A139,UNIC!C:H,6,0) -> - | I139: =VLOOKUP(H139,UNIC!H:J,3,0) -> - | J139: =VLOOKUP(Tabela1[[#This Row],[PLACA]],UNIC!C:V,20,0) -> R$ 2.000,00 | K139: =IFERROR(VALUE(VLOOKUP(Tabela1[[#This Row],[PLACA]],[1]Planilha2!$A:$F,3,0)),"") -> 0 | L139: =IFERROR(VALUE(VLOOKUP(Tabela1[[#This Row],[PLACA]],[1]Planilha2!$A:$F,4,0)),"") -> 789.59 | M139: =IFERROR(VALUE(VLOOKUP(Tabela1[[#This Row],[PLACA]],[1]Planilha2!$A:$F,5,0)),"") -> 715.6 | O139: =VLOOKUP(Tabela1[[#This Row],[PLACA]],BASE_LOCADORAS!B:F,5,0) -> #N/A | P139: =IF(Tabela1[[#This Row],[VENCIMENTO CONTRATO]]="SEM DADOS", "SEM DADOS", IF(ISERROR(DATEDIF(TODAY(),Tabela1[[#This Row],[VENCIMENTO CONTRATO]],"d")), "VENCIDO", IF(DATEDIF(TODAY(),Tabela1[[#This Row],[VENCIMENTO CONTRATO]],"d")>90, "EM DIAS", "ATENÇÃO" ) ) ) -> #N/A | Q139: =VLOOKUP(Tabela1[[#This Row],[PLACA]],BASE_LOCADORAS!B:G,6,0) -> #N/A | R139: =Tabela1[[#This Row],[VALOR LOCADORA]]=Tabela1[[#This Row],[GASTO ALUGUEL]] -> #N/A | S139: =UPPER(TEXT(Tabela1[[#This Row],[VENCIMENTO CONTRATO]],"MMM")) -> #N/A | T139: =IFERROR(YEAR(Tabela1[[#This Row],[VENCIMENTO CONTRATO]]),"-") -> - | U139: =VLOOKUP(Tabela1[[#This Row],[PLACA]],UNIC!C:T,18,0) -> PATIO | V139: =SUBSTITUTE(VLOOKUP(Tabela1[[#This Row],[PLACA]],UNIC!C:K,9,0),".", "") | W139: =VLOOKUP(Tabela1[[#This Row],[PLACA]],UNIC!C:M,10,0) -> 0 | X139: =VLOOKUP(Tabela1[[#This Row],[PLACA]],UNIC!C:M,11,0) -> 0 | Y139: =SUM(Tabela1[[#This Row],[GASTO COMBUSTÍVEL FEVEREIRO]:[GASTO COMBUSTÍVE ABRIL]]) -> 1505.19 | Z139: =IFERROR(AVERAGE(Tabela1[[#This Row],[GASTO COMBUSTÍVE ABRIL]:[GASTO COMBUSTÍVE MARÇO]]),"-") -> 752.595
A140: GER2786 | B140: =VLOOKUP(A140,UNIC!C:W,2,0) -> B4T 9000E | C140: =VLOOKUP(A140,UNIC!C:W,3,0) -> GERADOR | D140: =VLOOKUP(A140,UNIC!C:W,5,0) -> 2025 | E140: =VLOOKUP(A140,UNIC!C:W,21,0) -> EQUIPAMENTO | F140: =VLOOKUP(Tabela1[[#This Row],[PLACA]],UNIC!C:R,15,0) -> TO | G140: =VLOOKUP(Tabela1[[#This Row],[PLACA]],UNIC!C:R,16,0) -> NORTE | H140: =VLOOKUP(A140,UNIC!C:H,6,0) -> - | I140: =VLOOKUP(H140,UNIC!H:J,3,0) -> - | J140: =VLOOKUP(Tabela1[[#This Row],[PLACA]],UNIC!C:V,20,0) -> R$ 0,00 | K140: =IFERROR(VALUE(VLOOKUP(Tabela1[[#This Row],[PLACA]],[1]Planilha2!$A:$F,3,0)),"") -> 0 | L140: =IFERROR(VALUE(VLOOKUP(Tabela1[[#This Row],[PLACA]],[1]Planilha2!$A:$F,4,0)),"") -> 326.79 | M140: =IFERROR(VALUE(VLOOKUP(Tabela1[[#This Row],[PLACA]],[1]Planilha2!$A:$F,5,0)),"") -> 338.65 | O140: =VLOOKUP(Tabela1[[#This Row],[PLACA]],BASE_LOCADORAS!B:F,5,0) -> #N/A | P140: =IF(Tabela1[[#This Row],[VENCIMENTO CONTRATO]]="SEM DADOS", "SEM DADOS", IF(ISERROR(DATEDIF(TODAY(),Tabela1[[#This Row],[VENCIMENTO CONTRATO]],"d")), "VENCIDO", IF(DATEDIF(TODAY(),Tabela1[[#This Row],[VENCIMENTO CONTRATO]],"d")>90, "EM DIAS", "ATENÇÃO" ) ) ) -> #N/A | Q140: =VLOOKUP(Tabela1[[#This Row],[PLACA]],BASE_LOCADORAS!B:G,6,0) -> #N/A | R140: =Tabela1[[#This Row],[VALOR LOCADORA]]=Tabela1[[#This Row],[GASTO ALUGUEL]] -> #N/A | S140: =UPPER(TEXT(Tabela1[[#This Row],[VENCIMENTO CONTRATO]],"MMM")) -> #N/A | T140: =IFERROR(YEAR(Tabela1[[#This Row],[VENCIMENTO CONTRATO]]),"-") -> - | U140: =VLOOKUP(Tabela1[[#This Row],[PLACA]],UNIC!C:T,18,0) -> ATIVO | V140: =SUBSTITUTE(VLOOKUP(Tabela1[[#This Row],[PLACA]],UNIC!C:K,9,0),".", "") | W140: =VLOOKUP(Tabela1[[#This Row],[PLACA]],UNIC!C:M,10,0) -> 0 | X140: =VLOOKUP(Tabela1[[#This Row],[PLACA]],UNIC!C:M,11,0) -> 0 | Y140: =SUM(Tabela1[[#This Row],[GASTO COMBUSTÍVEL FEVEREIRO]:[GASTO COMBUSTÍVE ABRIL]]) -> 665.44 | Z140: =IFERROR(AVERAGE(Tabela1[[#This Row],[GASTO COMBUSTÍVE ABRIL]:[GASTO COMBUSTÍVE MARÇO]]),"-") -> 332.72
A141: EKL3749 | B141: =VLOOKUP(A141,UNIC!C:W,2,0) -> PUNTO | C141: =VLOOKUP(A141,UNIC!C:W,3,0) -> LEVE | D141: =VLOOKUP(A141,UNIC!C:W,5,0) -> 2009 | E141: =VLOOKUP(A141,UNIC!C:W,21,0) -> PARTICULAR | F141: =VLOOKUP(Tabela1[[#This Row],[PLACA]],UNIC!C:R,15,0) -> SP | G141: =VLOOKUP(Tabela1[[#This Row],[PLACA]],UNIC!C:R,16,0) -> SUDESTE | H141: =VLOOKUP(A141,UNIC!C:H,6,0) -> EMERSON PINHEIRO | I141: =VLOOKUP(H141,UNIC!H:J,3,0) -> COORDENADOR I | J141: =VLOOKUP(Tabela1[[#This Row],[PLACA]],UNIC!C:V,20,0) -> R$ 2.000,00 | K141: =IFERROR(VALUE(VLOOKUP(Tabela1[[#This Row],[PLACA]],[1]Planilha2!$A:$F,3,0)),"") -> 0 | L141: =IFERROR(VALUE(VLOOKUP(Tabela1[[#This Row],[PLACA]],[1]Planilha2!$A:$F,4,0)),"") -> 786.83 | M141: =IFERROR(VALUE(VLOOKUP(Tabela1[[#This Row],[PLACA]],[1]Planilha2!$A:$F,5,0)),"") -> 924.06 | O141: =VLOOKUP(Tabela1[[#This Row],[PLACA]],BASE_LOCADORAS!B:F,5,0) -> #N/A | P141: =IF(Tabela1[[#This Row],[VENCIMENTO CONTRATO]]="SEM DADOS", "SEM DADOS", IF(ISERROR(DATEDIF(TODAY(),Tabela1[[#This Row],[VENCIMENTO CONTRATO]],"d")), "VENCIDO", IF(DATEDIF(TODAY(),Tabela1[[#This Row],[VENCIMENTO CONTRATO]],"d")>90, "EM DIAS", "ATENÇÃO" ) ) ) -> #N/A | Q141: =VLOOKUP(Tabela1[[#This Row],[PLACA]],BASE_LOCADORAS!B:G,6,0) -> #N/A | R141: =Tabela1[[#This Row],[VALOR LOCADORA]]=Tabela1[[#This Row],[GASTO ALUGUEL]] -> #N/A | S141: =UPPER(TEXT(Tabela1[[#This Row],[VENCIMENTO CONTRATO]],"MMM")) -> #N/A | T141: =IFERROR(YEAR(Tabela1[[#This Row],[VENCIMENTO CONTRATO]]),"-") -> - | U141: =VLOOKUP(Tabela1[[#This Row],[PLACA]],UNIC!C:T,18,0) -> ATIVO | V141: =SUBSTITUTE(VLOOKUP(Tabela1[[#This Row],[PLACA]],UNIC!C:K,9,0),".", "") -> 99138 | W141: =VLOOKUP(Tabela1[[#This Row],[PLACA]],UNIC!C:M,10,0) -> 35001 | X141: =VLOOKUP(Tabela1[[#This Row],[PLACA]],UNIC!C:M,11,0) -> ADMINISTRATIVO | Y141: =SUM(Tabela1[[#This Row],[GASTO COMBUSTÍVEL FEVEREIRO]:[GASTO COMBUSTÍVE ABRIL]]) -> 1710.89 | Z141: =IFERROR(AVERAGE(Tabela1[[#This Row],[GASTO COMBUSTÍVE ABRIL]:[GASTO COMBUSTÍVE MARÇO]]),"-") -> 855.445
A142: OOA0977 | B142: =VLOOKUP(A142,UNIC!C:W,2,0) -> FIT | C142: =VLOOKUP(A142,UNIC!C:W,3,0) -> LEVE | D142: =VLOOKUP(A142,UNIC!C:W,5,0) -> 2023 | E142: =VLOOKUP(A142,UNIC!C:W,21,0) -> PARTICULAR | F142: =VLOOKUP(Tabela1[[#This Row],[PLACA]],UNIC!C:R,15,0) -> GO | G142: =VLOOKUP(Tabela1[[#This Row],[PLACA]],UNIC!C:R,16,0) -> CENTRO OESTE | H142: =VLOOKUP(A142,UNIC!C:H,6,0) -> LESLYE HUMBERTO PEREIRA RAMOS | I142: =VLOOKUP(H142,UNIC!H:J,3,0) -> ASSISTENTE DE FROTA | J142: =VLOOKUP(Tabela1[[#This Row],[PLACA]],UNIC!C:V,20,0) -> R$ 1.550,00 | K142: =IFERROR(VALUE(VLOOKUP(Tabela1[[#This Row],[PLACA]],[1]Planilha2!$A:$F,3,0)),"") -> 0 | L142: =IFERROR(VALUE(VLOOKUP(Tabela1[[#This Row],[PLACA]],[1]Planilha2!$A:$F,4,0)),"") -> 90.09 | M142: =IFERROR(VALUE(VLOOKUP(Tabela1[[#This Row],[PLACA]],[1]Planilha2!$A:$F,5,0)),"") -> 0 | O142: =VLOOKUP(Tabela1[[#This Row],[PLACA]],BASE_LOCADORAS!B:F,5,0) -> #N/A | P142: =IF(Tabela1[[#This Row],[VENCIMENTO CONTRATO]]="SEM DADOS", "SEM DADOS", IF(ISERROR(DATEDIF(TODAY(),Tabela1[[#This Row],[VENCIMENTO CONTRATO]],"d")), "VENCIDO", IF(DATEDIF(TODAY(),Tabela1[[#This Row],[VENCIMENTO CONTRATO]],"d")>90, "EM DIAS", "ATENÇÃO" ) ) ) -> #N/A | Q142: =VLOOKUP(Tabela1[[#This Row],[PLACA]],BASE_LOCADORAS!B:G,6,0) -> #N/A | R142: =Tabela1[[#This Row],[VALOR LOCADORA]]=Tabela1[[#This Row],[GASTO ALUGUEL]] -> #N/A | S142: =UPPER(TEXT(Tabela1[[#This Row],[VENCIMENTO CONTRATO]],"MMM")) -> #N/A | T142: =IFERROR(YEAR(Tabela1[[#This Row],[VENCIMENTO CONTRATO]]),"-") -> - | U142: =VLOOKUP(Tabela1[[#This Row],[PLACA]],UNIC!C:T,18,0) -> ATIVO | V142: =SUBSTITUTE(VLOOKUP(Tabela1[[#This Row],[PLACA]],UNIC!C:K,9,0),".", "") -> 99628 | W142: =VLOOKUP(Tabela1[[#This Row],[PLACA]],UNIC!C:M,10,0) -> 19019 | X142: =VLOOKUP(Tabela1[[#This Row],[PLACA]],UNIC!C:M,11,0) -> ADMINISTRATIVO | Y142: =SUM(Tabela1[[#This Row],[GASTO COMBUSTÍVEL FEVEREIRO]:[GASTO COMBUSTÍVE ABRIL]]) -> 90.09 | Z142: =IFERROR(AVERAGE(Tabela1[[#This Row],[GASTO COMBUSTÍVE ABRIL]:[GASTO COMBUSTÍVE MARÇO]]),"-") -> 45.045
A143: GER2781 | B143: =VLOOKUP(A143,UNIC!C:W,2,0) -> B4T 9000E | C143: =VLOOKUP(A143,UNIC!C:W,3,0) -> GERADOR | D143: =VLOOKUP(A143,UNIC!C:W,5,0) -> 2026 | E143: =VLOOKUP(A143,UNIC!C:W,21,0) -> EQUIPAMENTO | F143: =VLOOKUP(Tabela1[[#This Row],[PLACA]],UNIC!C:R,15,0) -> TO | G143: =VLOOKUP(Tabela1[[#This Row],[PLACA]],UNIC!C:R,16,0) -> NORTE | H143: =VLOOKUP(A143,UNIC!C:H,6,0) -> - | I143: =VLOOKUP(H143,UNIC!H:J,3,0) -> - | J143: =VLOOKUP(Tabela1[[#This Row],[PLACA]],UNIC!C:V,20,0) -> R$ 0,01 | K143: =IFERROR(VALUE(VLOOKUP(Tabela1[[#This Row],[PLACA]],[1]Planilha2!$A:$F,3,0)),"") -> 0 | L143: =IFERROR(VALUE(VLOOKUP(Tabela1[[#This Row],[PLACA]],[1]Planilha2!$A:$F,4,0)),"") -> 1669.79 | M143: =IFERROR(VALUE(VLOOKUP(Tabela1[[#This Row],[PLACA]],[1]Planilha2!$A:$F,5,0)),"") -> 432.13 | O143: =VLOOKUP(Tabela1[[#This Row],[PLACA]],BASE_LOCADORAS!B:F,5,0) -> #N/A | P143: =IF(Tabela1[[#This Row],[VENCIMENTO CONTRATO]]="SEM DADOS", "SEM DADOS", IF(ISERROR(DATEDIF(TODAY(),Tabela1[[#This Row],[VENCIMENTO CONTRATO]],"d")), "VENCIDO", IF(DATEDIF(TODAY(),Tabela1[[#This Row],[VENCIMENTO CONTRATO]],"d")>90, "EM DIAS", "ATENÇÃO" ) ) ) -> #N/A | Q143: =VLOOKUP(Tabela1[[#This Row],[PLACA]],BASE_LOCADORAS!B:G,6,0) -> #N/A | R143: =Tabela1[[#This Row],[VALOR LOCADORA]]=Tabela1[[#This Row],[GASTO ALUGUEL]] -> #N/A | S143: =UPPER(TEXT(Tabela1[[#This Row],[VENCIMENTO CONTRATO]],"MMM")) -> #N/A | T143: =IFERROR(YEAR(Tabela1[[#This Row],[VENCIMENTO CONTRATO]]),"-") -> - | U143: =VLOOKUP(Tabela1[[#This Row],[PLACA]],UNIC!C:T,18,0) -> ATIVO | V143: =SUBSTITUTE(VLOOKUP(Tabela1[[#This Row],[PLACA]],UNIC!C:K,9,0),".", "") | W143: =VLOOKUP(Tabela1[[#This Row],[PLACA]],UNIC!C:M,10,0) -> 0 | X143: =VLOOKUP(Tabela1[[#This Row],[PLACA]],UNIC!C:M,11,0) -> 0 | Y143: =SUM(Tabela1[[#This Row],[GASTO COMBUSTÍVEL FEVEREIRO]:[GASTO COMBUSTÍVE ABRIL]]) -> 2101.92 | Z143: =IFERROR(AVERAGE(Tabela1[[#This Row],[GASTO COMBUSTÍVE ABRIL]:[GASTO COMBUSTÍVE MARÇO]]),"-") -> 1050.96
A144: GER2785 | B144: =VLOOKUP(A144,UNIC!C:W,2,0) -> B4T 9000E | C144: =VLOOKUP(A144,UNIC!C:W,3,0) -> GERADOR | D144: =VLOOKUP(A144,UNIC!C:W,5,0) -> 2026 | E144: =VLOOKUP(A144,UNIC!C:W,21,0) -> EQUIPAMENTO | F144: =VLOOKUP(Tabela1[[#This Row],[PLACA]],UNIC!C:R,15,0) -> TO | G144: =VLOOKUP(Tabela1[[#This Row],[PLACA]],UNIC!C:R,16,0) -> NORTE | H144: =VLOOKUP(A144,UNIC!C:H,6,0) -> - | I144: =VLOOKUP(H144,UNIC!H:J,3,0) -> - | J144: =VLOOKUP(Tabela1[[#This Row],[PLACA]],UNIC!C:V,20,0) -> R$ 0,01 | K144: =IFERROR(VALUE(VLOOKUP(Tabela1[[#This Row],[PLACA]],[1]Planilha2!$A:$F,3,0)),"") -> 0 | L144: =IFERROR(VALUE(VLOOKUP(Tabela1[[#This Row],[PLACA]],[1]Planilha2!$A:$F,4,0)),"") -> 1639.53 | M144: =IFERROR(VALUE(VLOOKUP(Tabela1[[#This Row],[PLACA]],[1]Planilha2!$A:$F,5,0)),"") -> 0 | O144: =VLOOKUP(Tabela1[[#This Row],[PLACA]],BASE_LOCADORAS!B:F,5,0) -> #N/A | P144: =IF(Tabela1[[#This Row],[VENCIMENTO CONTRATO]]="SEM DADOS", "SEM DADOS", IF(ISERROR(DATEDIF(TODAY(),Tabela1[[#This Row],[VENCIMENTO CONTRATO]],"d")), "VENCIDO", IF(DATEDIF(TODAY(),Tabela1[[#This Row],[VENCIMENTO CONTRATO]],"d")>90, "EM DIAS", "ATENÇÃO" ) ) ) -> #N/A | Q144: =VLOOKUP(Tabela1[[#This Row],[PLACA]],BASE_LOCADORAS!B:G,6,0) -> #N/A | R144: =Tabela1[[#This Row],[VALOR LOCADORA]]=Tabela1[[#This Row],[GASTO ALUGUEL]] -> #N/A | S144: =UPPER(TEXT(Tabela1[[#This Row],[VENCIMENTO CONTRATO]],"MMM")) -> #N/A | T144: =IFERROR(YEAR(Tabela1[[#This Row],[VENCIMENTO CONTRATO]]),"-") -> - | U144: =VLOOKUP(Tabela1[[#This Row],[PLACA]],UNIC!C:T,18,0) -> ATIVO | V144: =SUBSTITUTE(VLOOKUP(Tabela1[[#This Row],[PLACA]],UNIC!C:K,9,0),".", "") | W144: =VLOOKUP(Tabela1[[#This Row],[PLACA]],UNIC!C:M,10,0) -> 0 | X144: =VLOOKUP(Tabela1[[#This Row],[PLACA]],UNIC!C:M,11,0) -> 0 | Y144: =SUM(Tabela1[[#This Row],[GASTO COMBUSTÍVEL FEVEREIRO]:[GASTO COMBUSTÍVE ABRIL]]) -> 1639.53 | Z144: =IFERROR(AVERAGE(Tabela1[[#This Row],[GASTO COMBUSTÍVE ABRIL]:[GASTO COMBUSTÍVE MARÇO]]),"-") -> 819.765
A145: GER2787 | B145: =VLOOKUP(A145,UNIC!C:W,2,0) -> B4T 9000E | C145: =VLOOKUP(A145,UNIC!C:W,3,0) -> GERADOR | D145: =VLOOKUP(A145,UNIC!C:W,5,0) -> 2026 | E145: =VLOOKUP(A145,UNIC!C:W,21,0) -> EQUIPAMENTO | F145: =VLOOKUP(Tabela1[[#This Row],[PLACA]],UNIC!C:R,15,0) -> TO | G145: =VLOOKUP(Tabela1[[#This Row],[PLACA]],UNIC!C:R,16,0) -> NORTE | H145: =VLOOKUP(A145,UNIC!C:H,6,0) -> - | I145: =VLOOKUP(H145,UNIC!H:J,3,0) -> - | J145: =VLOOKUP(Tabela1[[#This Row],[PLACA]],UNIC!C:V,20,0) -> R$ 0,01 | K145: =IFERROR(VALUE(VLOOKUP(Tabela1[[#This Row],[PLACA]],[1]Planilha2!$A:$F,3,0)),"") -> 0 | L145: =IFERROR(VALUE(VLOOKUP(Tabela1[[#This Row],[PLACA]],[1]Planilha2!$A:$F,4,0)),"") -> 913.97 | M145: =IFERROR(VALUE(VLOOKUP(Tabela1[[#This Row],[PLACA]],[1]Planilha2!$A:$F,5,0)),"") -> 1602.1 | O145: =VLOOKUP(Tabela1[[#This Row],[PLACA]],BASE_LOCADORAS!B:F,5,0) -> #N/A | P145: =IF(Tabela1[[#This Row],[VENCIMENTO CONTRATO]]="SEM DADOS", "SEM DADOS", IF(ISERROR(DATEDIF(TODAY(),Tabela1[[#This Row],[VENCIMENTO CONTRATO]],"d")), "VENCIDO", IF(DATEDIF(TODAY(),Tabela1[[#This Row],[VENCIMENTO CONTRATO]],"d")>90, "EM DIAS", "ATENÇÃO" ) ) ) -> #N/A | Q145: =VLOOKUP(Tabela1[[#This Row],[PLACA]],BASE_LOCADORAS!B:G,6,0) -> #N/A | R145: =Tabela1[[#This Row],[VALOR LOCADORA]]=Tabela1[[#This Row],[GASTO ALUGUEL]] -> #N/A | S145: =UPPER(TEXT(Tabela1[[#This Row],[VENCIMENTO CONTRATO]],"MMM")) -> #N/A | T145: =IFERROR(YEAR(Tabela1[[#This Row],[VENCIMENTO CONTRATO]]),"-") -> - | U145: =VLOOKUP(Tabela1[[#This Row],[PLACA]],UNIC!C:T,18,0) -> ATIVO | V145: =SUBSTITUTE(VLOOKUP(Tabela1[[#This Row],[PLACA]],UNIC!C:K,9,0),".", "") | W145: =VLOOKUP(Tabela1[[#This Row],[PLACA]],UNIC!C:M,10,0) -> 0 | X145: =VLOOKUP(Tabela1[[#This Row],[PLACA]],UNIC!C:M,11,0) -> 0 | Y145: =SUM(Tabela1[[#This Row],[GASTO COMBUSTÍVEL FEVEREIRO]:[GASTO COMBUSTÍVE ABRIL]]) -> 2516.07 | Z145: =IFERROR(AVERAGE(Tabela1[[#This Row],[GASTO COMBUSTÍVE ABRIL]:[GASTO COMBUSTÍVE MARÇO]]),"-") -> 1258.035
A146: JWR8D42 | B146: =VLOOKUP(A146,UNIC!C:W,2,0) -> CELTA | C146: =VLOOKUP(A146,UNIC!C:W,3,0) -> LEVE | D146: =VLOOKUP(A146,UNIC!C:W,5,0) -> 2012 | E146: =VLOOKUP(A146,UNIC!C:W,21,0) -> PARTICULAR | F146: =VLOOKUP(Tabela1[[#This Row],[PLACA]],UNIC!C:R,15,0) -> AM | G146: =VLOOKUP(Tabela1[[#This Row],[PLACA]],UNIC!C:R,16,0) -> NORTE | H146: =VLOOKUP(A146,UNIC!C:H,6,0) -> - | I146: =VLOOKUP(H146,UNIC!H:J,3,0) -> - | J146: =VLOOKUP(Tabela1[[#This Row],[PLACA]],UNIC!C:V,20,0) -> R$ 0,00 | K146: =IFERROR(VALUE(VLOOKUP(Tabela1[[#This Row],[PLACA]],[1]Planilha2!$A:$F,3,0)),"") -> 0 | L146: =IFERROR(VALUE(VLOOKUP(Tabela1[[#This Row],[PLACA]],[1]Planilha2!$A:$F,4,0)),"") -> 257.7 | M146: =IFERROR(VALUE(VLOOKUP(Tabela1[[#This Row],[PLACA]],[1]Planilha2!$A:$F,5,0)),"") -> 0 | O146: =VLOOKUP(Tabela1[[#This Row],[PLACA]],BASE_LOCADORAS!B:F,5,0) -> #N/A | P146: =IF(Tabela1[[#This Row],[VENCIMENTO CONTRATO]]="SEM DADOS", "SEM DADOS", IF(ISERROR(DATEDIF(TODAY(),Tabela1[[#This Row],[VENCIMENTO CONTRATO]],"d")), "VENCIDO", IF(DATEDIF(TODAY(),Tabela1[[#This Row],[VENCIMENTO CONTRATO]],"d")>90, "EM DIAS", "ATENÇÃO" ) ) ) -> #N/A | Q146: =VLOOKUP(Tabela1[[#This Row],[PLACA]],BASE_LOCADORAS!B:G,6,0) -> #N/A | R146: =Tabela1[[#This Row],[VALOR LOCADORA]]=Tabela1[[#This Row],[GASTO ALUGUEL]] -> #N/A | S146: =UPPER(TEXT(Tabela1[[#This Row],[VENCIMENTO CONTRATO]],"MMM")) -> #N/A | T146: =IFERROR(YEAR(Tabela1[[#This Row],[VENCIMENTO CONTRATO]]),"-") -> - | U146: =VLOOKUP(Tabela1[[#This Row],[PLACA]],UNIC!C:T,18,0) -> PATIO | V146: =SUBSTITUTE(VLOOKUP(Tabela1[[#This Row],[PLACA]],UNIC!C:K,9,0),".", "") | W146: =VLOOKUP(Tabela1[[#This Row],[PLACA]],UNIC!C:M,10,0) -> 0 | X146: =VLOOKUP(Tabela1[[#This Row],[PLACA]],UNIC!C:M,11,0) -> 0 | Y146: =SUM(Tabela1[[#This Row],[GASTO COMBUSTÍVEL FEVEREIRO]:[GASTO COMBUSTÍVE ABRIL]]) -> 257.7 | Z146: =IFERROR(AVERAGE(Tabela1[[#This Row],[GASTO COMBUSTÍVE ABRIL]:[GASTO COMBUSTÍVE MARÇO]]),"-") -> 128.85
A147: QUL9I64 | B147: =VLOOKUP(A147,UNIC!C:W,2,0) -> KA | C147: =VLOOKUP(A147,UNIC!C:W,3,0) -> LEVE | D147: =VLOOKUP(A147,UNIC!C:W,5,0) -> 2012 | E147: =VLOOKUP(A147,UNIC!C:W,21,0) -> PARTICULAR | F147: =VLOOKUP(Tabela1[[#This Row],[PLACA]],UNIC!C:R,15,0) -> AM | G147: =VLOOKUP(Tabela1[[#This Row],[PLACA]],UNIC!C:R,16,0) -> NORTE | H147: =VLOOKUP(A147,UNIC!C:H,6,0) -> - | I147: =VLOOKUP(H147,UNIC!H:J,3,0) -> - | J147: =VLOOKUP(Tabela1[[#This Row],[PLACA]],UNIC!C:V,20,0) -> R$ 0,00 | K147: =IFERROR(VALUE(VLOOKUP(Tabela1[[#This Row],[PLACA]],[1]Planilha2!$A:$F,3,0)),"") -> 0 | L147: =IFERROR(VALUE(VLOOKUP(Tabela1[[#This Row],[PLACA]],[1]Planilha2!$A:$F,4,0)),"") -> 459.98 | M147: =IFERROR(VALUE(VLOOKUP(Tabela1[[#This Row],[PLACA]],[1]Planilha2!$A:$F,5,0)),"") -> 459.98 | O147: =VLOOKUP(Tabela1[[#This Row],[PLACA]],BASE_LOCADORAS!B:F,5,0) -> #N/A | P147: =IF(Tabela1[[#This Row],[VENCIMENTO CONTRATO]]="SEM DADOS", "SEM DADOS", IF(ISERROR(DATEDIF(TODAY(),Tabela1[[#This Row],[VENCIMENTO CONTRATO]],"d")), "VENCIDO", IF(DATEDIF(TODAY(),Tabela1[[#This Row],[VENCIMENTO CONTRATO]],"d")>90, "EM DIAS", "ATENÇÃO" ) ) ) -> #N/A | Q147: =VLOOKUP(Tabela1[[#This Row],[PLACA]],BASE_LOCADORAS!B:G,6,0) -> #N/A | R147: =Tabela1[[#This Row],[VALOR LOCADORA]]=Tabela1[[#This Row],[GASTO ALUGUEL]] -> #N/A | S147: =UPPER(TEXT(Tabela1[[#This Row],[VENCIMENTO CONTRATO]],"MMM")) -> #N/A | T147: =IFERROR(YEAR(Tabela1[[#This Row],[VENCIMENTO CONTRATO]]),"-") -> - | U147: =VLOOKUP(Tabela1[[#This Row],[PLACA]],UNIC!C:T,18,0) -> ATIVO | V147: =SUBSTITUTE(VLOOKUP(Tabela1[[#This Row],[PLACA]],UNIC!C:K,9,0),".", "") | W147: =VLOOKUP(Tabela1[[#This Row],[PLACA]],UNIC!C:M,10,0) -> 0 | X147: =VLOOKUP(Tabela1[[#This Row],[PLACA]],UNIC!C:M,11,0) -> 0 | Y147: =SUM(Tabela1[[#This Row],[GASTO COMBUSTÍVEL FEVEREIRO]:[GASTO COMBUSTÍVE ABRIL]]) -> 919.96 | Z147: =IFERROR(AVERAGE(Tabela1[[#This Row],[GASTO COMBUSTÍVE ABRIL]:[GASTO COMBUSTÍVE MARÇO]]),"-") -> 459.98
A148: PHH2066 | B148: =VLOOKUP(A148,UNIC!C:W,2,0) -> GOL | C148: =VLOOKUP(A148,UNIC!C:W,3,0) -> LEVE | D148: =VLOOKUP(A148,UNIC!C:W,5,0) -> 2012 | E148: =VLOOKUP(A148,UNIC!C:W,21,0) -> PARTICULAR | F148: =VLOOKUP(Tabela1[[#This Row],[PLACA]],UNIC!C:R,15,0) -> AM | G148: =VLOOKUP(Tabela1[[#This Row],[PLACA]],UNIC!C:R,16,0) -> NORTE | H148: =VLOOKUP(A148,UNIC!C:H,6,0) -> - | I148: =VLOOKUP(H148,UNIC!H:J,3,0) -> - | J148: =VLOOKUP(Tabela1[[#This Row],[PLACA]],UNIC!C:V,20,0) -> R$ 0,00 | K148: =IFERROR(VALUE(VLOOKUP(Tabela1[[#This Row],[PLACA]],[1]Planilha2!$A:$F,3,0)),"") -> 0 | L148: =IFERROR(VALUE(VLOOKUP(Tabela1[[#This Row],[PLACA]],[1]Planilha2!$A:$F,4,0)),"") -> 230 | M148: =IFERROR(VALUE(VLOOKUP(Tabela1[[#This Row],[PLACA]],[1]Planilha2!$A:$F,5,0)),"") -> 0 | O148: =VLOOKUP(Tabela1[[#This Row],[PLACA]],BASE_LOCADORAS!B:F,5,0) -> #N/A | P148: =IF(Tabela1[[#This Row],[VENCIMENTO CONTRATO]]="SEM DADOS", "SEM DADOS", IF(ISERROR(DATEDIF(TODAY(),Tabela1[[#This Row],[VENCIMENTO CONTRATO]],"d")), "VENCIDO", IF(DATEDIF(TODAY(),Tabela1[[#This Row],[VENCIMENTO CONTRATO]],"d")>90, "EM DIAS", "ATENÇÃO" ) ) ) -> #N/A | Q148: =VLOOKUP(Tabela1[[#This Row],[PLACA]],BASE_LOCADORAS!B:G,6,0) -> #N/A | R148: =Tabela1[[#This Row],[VALOR LOCADORA]]=Tabela1[[#This Row],[GASTO ALUGUEL]] -> #N/A | S148: =UPPER(TEXT(Tabela1[[#This Row],[VENCIMENTO CONTRATO]],"MMM")) -> #N/A | T148: =IFERROR(YEAR(Tabela1[[#This Row],[VENCIMENTO CONTRATO]]),"-") -> - | U148: =VLOOKUP(Tabela1[[#This Row],[PLACA]],UNIC!C:T,18,0) -> ATIVO | V148: =SUBSTITUTE(VLOOKUP(Tabela1[[#This Row],[PLACA]],UNIC!C:K,9,0),".", "") | W148: =VLOOKUP(Tabela1[[#This Row],[PLACA]],UNIC!C:M,10,0) -> 0 | X148: =VLOOKUP(Tabela1[[#This Row],[PLACA]],UNIC!C:M,11,0) -> 0 | Y148: =SUM(Tabela1[[#This Row],[GASTO COMBUSTÍVEL FEVEREIRO]:[GASTO COMBUSTÍVE ABRIL]]) -> 230 | Z148: =IFERROR(AVERAGE(Tabela1[[#This Row],[GASTO COMBUSTÍVE ABRIL]:[GASTO COMBUSTÍVE MARÇO]]),"-") -> 115
A149: OAK6I24 | B149: =VLOOKUP(A149,UNIC!C:W,2,0) -> SAVEIRO | C149: =VLOOKUP(A149,UNIC!C:W,3,0) -> UTILITARIO | D149: =VLOOKUP(A149,UNIC!C:W,5,0) -> 2012 | E149: =VLOOKUP(A149,UNIC!C:W,21,0) -> PARTICULAR | F149: =VLOOKUP(Tabela1[[#This Row],[PLACA]],UNIC!C:R,15,0) -> AM | G149: =VLOOKUP(Tabela1[[#This Row],[PLACA]],UNIC!C:R,16,0) -> NORTE | H149: =VLOOKUP(A149,UNIC!C:H,6,0) -> - | I149: =VLOOKUP(H149,UNIC!H:J,3,0) -> - | J149: =VLOOKUP(Tabela1[[#This Row],[PLACA]],UNIC!C:V,20,0) -> R$ 0,00 | K149: =IFERROR(VALUE(VLOOKUP(Tabela1[[#This Row],[PLACA]],[1]Planilha2!$A:$F,3,0)),"") | L149: =IFERROR(VALUE(VLOOKUP(Tabela1[[#This Row],[PLACA]],[1]Planilha2!$A:$F,4,0)),"") | M149: =IFERROR(VALUE(VLOOKUP(Tabela1[[#This Row],[PLACA]],[1]Planilha2!$A:$F,5,0)),"") | O149: =VLOOKUP(Tabela1[[#This Row],[PLACA]],BASE_LOCADORAS!B:F,5,0) -> #N/A | P149: =IF(Tabela1[[#This Row],[VENCIMENTO CONTRATO]]="SEM DADOS", "SEM DADOS", IF(ISERROR(DATEDIF(TODAY(),Tabela1[[#This Row],[VENCIMENTO CONTRATO]],"d")), "VENCIDO", IF(DATEDIF(TODAY(),Tabela1[[#This Row],[VENCIMENTO CONTRATO]],"d")>90, "EM DIAS", "ATENÇÃO" ) ) ) -> #N/A | Q149: =VLOOKUP(Tabela1[[#This Row],[PLACA]],BASE_LOCADORAS!B:G,6,0) -> #N/A | R149: =Tabela1[[#This Row],[VALOR LOCADORA]]=Tabela1[[#This Row],[GASTO ALUGUEL]] -> #N/A | S149: =UPPER(TEXT(Tabela1[[#This Row],[VENCIMENTO CONTRATO]],"MMM")) -> #N/A | T149: =IFERROR(YEAR(Tabela1[[#This Row],[VENCIMENTO CONTRATO]]),"-") -> - | U149: =VLOOKUP(Tabela1[[#This Row],[PLACA]],UNIC!C:T,18,0) -> ATIVO | V149: =SUBSTITUTE(VLOOKUP(Tabela1[[#This Row],[PLACA]],UNIC!C:K,9,0),".", "") | W149: =VLOOKUP(Tabela1[[#This Row],[PLACA]],UNIC!C:M,10,0) -> 0 | X149: =VLOOKUP(Tabela1[[#This Row],[PLACA]],UNIC!C:M,11,0) -> 0 | Y149: =SUM(Tabela1[[#This Row],[GASTO COMBUSTÍVEL FEVEREIRO]:[GASTO COMBUSTÍVE ABRIL]]) -> 0 | Z149: =IFERROR(AVERAGE(Tabela1[[#This Row],[GASTO COMBUSTÍVE ABRIL]:[GASTO COMBUSTÍVE MARÇO]]),"-") -> -
A150: OAJ3I23 | B150: =VLOOKUP(A150,UNIC!C:W,2,0) -> FOX | C150: =VLOOKUP(A150,UNIC!C:W,3,0) -> LEVE | D150: =VLOOKUP(A150,UNIC!C:W,5,0) -> 2012 | E150: =VLOOKUP(A150,UNIC!C:W,21,0) -> PARTICULAR | F150: =VLOOKUP(Tabela1[[#This Row],[PLACA]],UNIC!C:R,15,0) -> AM | G150: =VLOOKUP(Tabela1[[#This Row],[PLACA]],UNIC!C:R,16,0) -> NORTE | H150: =VLOOKUP(A150,UNIC!C:H,6,0) -> - | I150: =VLOOKUP(H150,UNIC!H:J,3,0) -> - | J150: =VLOOKUP(Tabela1[[#This Row],[PLACA]],UNIC!C:V,20,0) -> R$ 0,00 | K150: =IFERROR(VALUE(VLOOKUP(Tabela1[[#This Row],[PLACA]],[1]Planilha2!$A:$F,3,0)),"") | L150: =IFERROR(VALUE(VLOOKUP(Tabela1[[#This Row],[PLACA]],[1]Planilha2!$A:$F,4,0)),"") | M150: =IFERROR(VALUE(VLOOKUP(Tabela1[[#This Row],[PLACA]],[1]Planilha2!$A:$F,5,0)),"") | O150: =VLOOKUP(Tabela1[[#This Row],[PLACA]],BASE_LOCADORAS!B:F,5,0) -> #N/A | P150: =IF(Tabela1[[#This Row],[VENCIMENTO CONTRATO]]="SEM DADOS", "SEM DADOS", IF(ISERROR(DATEDIF(TODAY(),Tabela1[[#This Row],[VENCIMENTO CONTRATO]],"d")), "VENCIDO", IF(DATEDIF(TODAY(),Tabela1[[#This Row],[VENCIMENTO CONTRATO]],"d")>90, "EM DIAS", "ATENÇÃO" ) ) ) -> #N/A | Q150: =VLOOKUP(Tabela1[[#This Row],[PLACA]],BASE_LOCADORAS!B:G,6,0) -> #N/A | R150: =Tabela1[[#This Row],[VALOR LOCADORA]]=Tabela1[[#This Row],[GASTO ALUGUEL]] -> #N/A | S150: =UPPER(TEXT(Tabela1[[#This Row],[VENCIMENTO CONTRATO]],"MMM")) -> #N/A | T150: =IFERROR(YEAR(Tabela1[[#This Row],[VENCIMENTO CONTRATO]]),"-") -> - | U150: =VLOOKUP(Tabela1[[#This Row],[PLACA]],UNIC!C:T,18,0) -> ATIVO | V150: =SUBSTITUTE(VLOOKUP(Tabela1[[#This Row],[PLACA]],UNIC!C:K,9,0),".", "") | W150: =VLOOKUP(Tabela1[[#This Row],[PLACA]],UNIC!C:M,10,0) -> 0 | X150: =VLOOKUP(Tabela1[[#This Row],[PLACA]],UNIC!C:M,11,0) -> 0 | Y150: =SUM(Tabela1[[#This Row],[GASTO COMBUSTÍVEL FEVEREIRO]:[GASTO COMBUSTÍVE ABRIL]]) -> 0 | Z150: =IFERROR(AVERAGE(Tabela1[[#This Row],[GASTO COMBUSTÍVE ABRIL]:[GASTO COMBUSTÍVE MARÇO]]),"-") -> -
... A1672: PWG3B87 | B1672: =VLOOKUP(A1672,UNIC!C:W,2,0) -> STRADA | C1672: =VLOOKUP(A1672,UNIC!C:W,3,0) -> UTILITARIO | D1672: =VLOOKUP(A1672,UNIC!C:W,5,0) -> 2024 | E1672: =VLOOKUP(A1672,UNIC!C:W,21,0) -> LOCALIZA | F1672: =VLOOKUP(Tabela1[[#This Row],[PLACA]],UNIC!C:R,15,0) -> AM | G1672: =VLOOKUP(Tabela1[[#This Row],[PLACA]],UNIC!C:R,16,0) -> NORTE | H1672: =VLOOKUP(A1672,UNIC!C:H,6,0) -> CAIO DANESSON DE JESUS ROCHA | I1672: =VLOOKUP(H1672,UNIC!H:J,3,0) -> TECNICO DE FIBRA OPTICA I | J1672: =VLOOKUP(Tabela1[[#This Row],[PLACA]],UNIC!C:V,20,0) -> R$ 2.559,17 | K1672: =IFERROR(VALUE(VLOOKUP(Tabela1[[#This Row],[PLACA]],[1]Planilha2!$A:$F,3,0)),"") -> 980.96 | L1672: =IFERROR(VALUE(VLOOKUP(Tabela1[[#This Row],[PLACA]],[1]Planilha2!$A:$F,4,0)),"") -> 1305.92 | M1672: =IFERROR(VALUE(VLOOKUP(Tabela1[[#This Row],[PLACA]],[1]Planilha2!$A:$F,5,0)),"") -> 728.54 | O1672: =VLOOKUP(Tabela1[[#This Row],[PLACA]],BASE_LOCADORAS!B:F,5,0) -> 07/08/2027 | P1672: =IF(Tabela1[[#This Row],[VENCIMENTO CONTRATO]]="SEM DADOS", "SEM DADOS", IF(ISERROR(DATEDIF(TODAY(),Tabela1[[#This Row],[VENCIMENTO CONTRATO]],"d")), "VENCIDO", IF(DATEDIF(TODAY(),Tabela1[[#This Row],[VENCIMENTO CONTRATO]],"d")>90, "EM DIAS", "ATENÇÃO" ) ) ) -> EM DIAS | Q1672: =VLOOKUP(Tabela1[[#This Row],[PLACA]],BASE_LOCADORAS!B:G,6,0) -> 2559.17 | R1672: =Tabela1[[#This Row],[VALOR LOCADORA]]=Tabela1[[#This Row],[GASTO ALUGUEL]] -> FALSE | S1672: =UPPER(TEXT(Tabela1[[#This Row],[VENCIMENTO CONTRATO]],"MMM")) -> AGO | T1672: =IFERROR(YEAR(Tabela1[[#This Row],[VENCIMENTO CONTRATO]]),"-") -> 2027 | U1672: =VLOOKUP(Tabela1[[#This Row],[PLACA]],UNIC!C:T,18,0) -> ATIVO | V1672: =SUBSTITUTE(VLOOKUP(Tabela1[[#This Row],[PLACA]],UNIC!C:K,9,0),".", "") -> 11031 | W1672: =VLOOKUP(Tabela1[[#This Row],[PLACA]],UNIC!C:M,10,0) -> 14001 | X1672: =VLOOKUP(Tabela1[[#This Row],[PLACA]],UNIC!C:M,11,0) -> VIVO | Y1672: =SUM(Tabela1[[#This Row],[GASTO COMBUSTÍVEL FEVEREIRO]:[GASTO COMBUSTÍVE ABRIL]]) -> 3015.42 | Z1672: =IFERROR(AVERAGE(Tabela1[[#This Row],[GASTO COMBUSTÍVE ABRIL]:[GASTO COMBUSTÍVE MARÇO]]),"-") -> 1017.23

Sheet UNIC
A1: Status Unic | B1: ID | C1: Veículo | D1: Modelo do Veículo | E1: Tipo do Veículo | F1: Ano Veículo | G1: Ano Modelo do Veículo | H1: Nome do Condutor | I1: Matrícula do Condutor | J1: Cargo do Condutor | K1: Centro de Custo | L1: Item Contábil | M1: Cliente | N1: Começo de Contrato | O1: Fim de Contrato | P1: Quilometragem | Q1: UF | R1: Base Regional | S1: Base Operacional | T1: Status | U1: Modelo | V1: Aluguel | W1: Locadora | X1: Atualizado Por | Y1: Atualizado Em | Z1: Observações
A2: Novo | B2: 2809 | C2: UAS3B92 | D2: SAVEIRO | E2: UTILITARIO | F2: 2025 | G2: 2026 | H2: - | I2: - | J2: - | N2: 17/04/2026 00:00:00 | Q2: RS | R2: SUL | S2: PORTO ALEGRE | T2: PATIO | U2: SAVEIRO | V2: R$ 0,00 | W2: MOVIDA | X2: felipe.miranda@ondacom.com | Y2: 17/04/2026 15:37:05
A3: Novo | B3: 2808 | C3: UAS3I79 | D3: SAVEIRO | E3: UTILITARIO | F3: 2025 | G3: 2026 | H3: - | I3: - | J3: - | N3: 17/04/2026 00:00:00 | Q3: RS | R3: SUL | S3: PORTO ALEGRE | T3: PATIO | U3: SAVEIRO | V3: R$ 0,00 | W3: MOVIDA | X3: felipe.miranda@ondacom.com | Y3: 17/04/2026 15:35:47
A4: Novo | B4: 2807 | C4: UAS2J80 | D4: SAVEIRO | E4: UTILITARIO | F4: 2025 | G4: 2026 | H4: - | I4: - | J4: - | N4: 17/04/2026 00:00:00 | Q4: RS | R4: SUL | S4: PORTO ALEGRE | T4: PATIO | U4: SAVEIRO | V4: R$ 0,00 | W4: MOVIDA | X4: felipe.miranda@ondacom.com | Y4: 17/04/2026 15:35:06
A5: Novo | B5: 2806 | C5: UAS3E08 | D5: SAVEIRO | E5: UTILITARIO | F5: 2025 | G5: 2026 | H5: - | I5: - | J5: - | N5: 17/04/2026 00:00:00 | Q5: RS | R5: SUL | S5: PORTO ALEGRE | T5: PATIO | U5: SAVEIRO | V5: R$ 0,00 | W5: MOVIDA | X5: felipe.miranda@ondacom.com | Y5: 17/04/2026 15:34:16
A6: Novo | B6: 2805 | C6: UAS3G94 | D6: SAVEIRO | E6: UTILITARIO | F6: 2025 | G6: 2026 | H6: - | I6: - | J6: - | N6: 17/04/2026 00:00:00 | Q6: RS | R6: SUL | S6: PORTO ALEGRE | T6: PATIO | U6: SAVEIRO | V6: R$ 0,00 | W6: MOVIDA | X6: felipe.miranda@ondacom.com | Y6: 17/04/2026 15:33:01
A7: Novo | B7: 2804 | C7: UAS0H69 | D7: SAVEIRO | E7: UTILITARIO | F7: 2025 | G7: 2026 | H7: - | I7: - | J7: - | Q7: RS | R7: SUL | S7: PORTO ALEGRE | T7: PATIO | U7: SAVEIRO | V7: R$ 0,00 | W7: MOVIDA | X7: felipe.miranda@ondacom.com | Y7: 17/04/2026 10:29:48
A8: Novo | B8: 2803 | C8: UAS0H57 | D8: SAVEIRO | E8: UTILITARIO | F8: 2025 | G8: 2026 | H8: - | I8: - | J8: - | N8: 17/04/2026 00:00:00 | Q8: RS | R8: SUL | S8: PORTO ALEGRE | T8: PATIO | U8: SAVEIRO | V8: R$ 0,00 | W8: MOVIDA | X8: felipe.miranda@ondacom.com | Y8: 17/04/2026 10:28:51
A9: Novo | B9: 2802 | C9: UAS0H48 | D9: SAVEIRO | E9: UTILITARIO | F9: 2025 | G9: 2026 | H9: - | I9: - | J9: - | Q9: RS | R9: SUL | S9: PORTO ALEGRE | T9: PATIO | U9: SAVEIRO | V9: R$ 0,00 | W9: MOVIDA | X9: felipe.miranda@ondacom.com | Y9: 17/04/2026 10:28:10
A10: Novo | B10: 2801 | C10: UAS0H36 | D10: SAVEIRO | E10: UTILITARIO | F10: 2025 | G10: 2026 | H10: - | I10: - | J10: - | Q10: RS | R10: SUL | S10: PORTO ALEGRE | T10: PATIO | U10: SAVEIRO | V10: R$ 2.026,00 | W10: MOVIDA | X10: felipe.miranda@ondacom.com | Y10: 17/04/2026 10:27:26
A11: Novo | B11: 2800 | C11: UAS0H21 | D11: SAVEIRO | E11: UTILITARIO | F11: 2025 | G11: 2026 | H11: - | I11: - | J11: - | N11: 17/04/2026 00:00:00 | Q11: RS | R11: SUL | S11: PORTO ALEGRE | T11: PATIO | U11: SAVEIRO | V11: R$ 0,00 | W11: MOVIDA | X11: felipe.miranda@ondacom.com | Y11: 17/04/2026 10:26:49
A12: Novo | B12: 2799 | C12: UAS0G99 | D12: SAVEIRO | E12: UTILITARIO | F12: 2025 | G12: 2026 | H12: - | I12: - | J12: - | N12: 17/04/2026 00:00:00 | Q12: RS | R12: SUL | S12: PORTO ALEGRE | T12: PATIO | U12: SAVEIRO | V12: R$ 0,00 | W12: MOVIDA | X12: felipe.miranda@ondacom.com | Y12: 17/04/2026 10:24:38
A13: Novo | B13: 2798 | C13: UAS0G93 | D13: SAVEIRO | E13: UTILITARIO | F13: 2025 | G13: 2026 | H13: - | I13: - | J13: - | N13: 17/04/2026 00:00:00 | Q13: RS | R13: SUL | S13: PORTO ALEGRE | T13: PATIO | U13: SAVEIRO | V13: R$ 0,00 | W13: MOVIDA | X13: felipe.miranda@ondacom.com | Y13: 17/04/2026 10:23:45
A14: Novo | B14: 2797 | C14: UAS0G87 | D14: SAVEIRO | E14: UTILITARIO | F14: 2025 | G14: 2026 | H14: - | I14: - | J14: - | Q14: RS | R14: SUL | S14: PORTO ALEGRE | T14: PATIO | U14: SAVEIRO | V14: R$ 0,00 | W14: MOVIDA | X14: felipe.miranda@ondacom.com | Y14: 17/04/2026 10:22:41
A15: Novo | B15: 2796 | C15: UAS0G80 | D15: SAVEIRO | E15: UTILITARIO | F15: 2025 | G15: 2026 | H15: - | I15: - | J15: - | N15: 17/04/2026 00:00:00 | Q15: RS | R15: SUL | S15: PORTO ALEGRE | T15: PATIO | U15: SAVEIRO | V15: R$ 0,00 | W15: MOVIDA | X15: felipe.miranda@ondacom.com | Y15: 17/04/2026 10:21:59
A16: Novo | B16: 2795 | C16: UAS0G73 | D16: SAVEIRO | E16: UTILITARIO | F16: 2025 | G16: 2026 | H16: - | I16: - | J16: - | N16: 17/04/2026 00:00:00 | Q16: RS | R16: SUL | S16: PORTO ALEGRE | T16: PATIO | U16: SAVEIRO | V16: R$ 0,00 | W16: MOVIDA | X16: felipe.miranda@ondacom.com | Y16: 17/04/2026 10:20:20
A17: Novo | B17: 2794 | C17: UAS0G53 | D17: SAVEIRO | E17: UTILITARIO | F17: 2026 | G17: 2025 | H17: - | I17: - | J17: - | N17: 17/04/2026 00:00:00 | Q17: RS | R17: SUL | S17: PORTO ALEGRE | T17: PATIO | U17: SAVEIRO | V17: R$ 0,00 | W17: MOVIDA | X17: felipe.miranda@ondacom.com | Y17: 17/04/2026 10:18:32
A18: Novo | B18: 2793 | C18: UDR0A37 | D18: HILUX | E18: 4X4 | F18: 2026 | G18: 2025 | H18: - | I18: - | J18: - | N18: 16/04/2026 00:00:00 | Q18: PR | R18: SUL | S18: CURITIBA | T18: PATIO | U18: HILUX | V18: R$ 0,00 | W18: MOVIDA | X18: felipe.miranda@ondacom.com | Y18: 16/04/2026 13:30:48
A19: Atualizado | B19: 2792 | C19: UAS0C60 | D19: SAVEIRO | E19: UTILITARIO | F19: 2026 | G19: 2025 | H19: EDUARDO DA SILVA MARTINS | I19: 8289 | J19: ASSISTENTE TEC. DE MANUTENCAO DE PI III | K19: 12.08.1 | L19: 26196 | M19: TIM MOVEL | N19: 09/04/2026 00:00:00 | Q19: PR | R19: SUL | S19: LONDRINA | T19: ATIVO | U19: SAVEIRO | V19: R$ 0,00 | W19: MOVIDA | X19: samara.pereira@ondacom.com | Y19: 16/04/2026 12:24:33
A20: Atualizado | B20: 2791 | C20: UAS0C78 | D20: SAVEIRO | E20: UTILITARIO | F20: 2026 | G20: 2025 | H20: JULIO RODRIGUES NETO | I20: 9374 | J20: TECNICO DE MANUTENCAO PI I | K20: 12.08.1 | L20: 26010 | M20: TIM MOVEL | N20: 09/04/2026 00:00:00 | Q20: PR | R20: SUL | S20: WENCESLAU BRAZ | T20: ATIVO | U20: SAVEIRO | V20: R$ 0,00 | W20: MOVIDA | X20: samara.pereira@ondacom.com | Y20: 16/04/2026 11:45:28
A21: Atualizado | B21: 2790 | C21: UAS0G64 | D21: SAVEIRO | E21: UTILITARIO | F21: 2026 | G21: 2025 | H21: JONATAN LEMES SANCHES | I21: 9196 | J21: ASSISTENTE TEC. DE MANUTENCAO DE PI II | K21: 12.08.1 | L21: 31292 | M21: TIM MOVEL | N21: 16/04/2026 00:00:00 | Q21: PR | R21: SUL | S21: CURITIBA | T21: ATIVO | U21: SAVEIRO | V21: R$ 0,00 | W21: MOVIDA | X21: samara.pereira@ondacom.com | Y21: 16/04/2026 17:30:55
A22: Atualizado | B22: 2789 | C22: UAS3F27 | D22: SAVEIRO | E22: UTILITARIO | F22: 2026 | G22: 2025 | H22: CESAR GIOVANE COLMAN DE VARGAS | I22: 9781 | J22: TECNICO DE MANUTENCAO PI II | K22: 12.08.1 | L22: 31001 | M22: TIM MOVEL | N22: 16/04/2026 00:00:00 | Q22: RS | R22: SUL | S22: PORTO ALEGRE | T22: ATIVO | U22: SAVEIRO | V22: R$ 0,00 | W22: MOVIDA | X22: samara.pereira@ondacom.com | Y22: 16/04/2026 17:33:12
A23: Atualizado | B23: 2788 | C23: TEE3I23 | D23: ARGO | E23: LEVE | F23: 2025 | G23: 2025 | H23: WAGNER ALCANTARA DE CAMARGO BARRETO | I23: 9408 | J23: SUPERVISOR DE ASSISTENCIA TECNICA I | K23: 11.01.5 | L23: 35001 | M23: VIVO | Q23: SP | R23: SUDESTE | S23: SÃO PAULO | T23: ATIVO | U23: ARGO | V23: R$ 0,00 | W23: LOCALIZA | X23: 8989BRUNA RIBEIRO LIMA | Y23: 16/04/2026 11:11:55
A24: Atualizado | B24: 2787 | C24: UAS0C85 | D24: SAVEIRO | E24: UTILITARIO | F24: 2025 | G24: 2025 | H24: CRISTIANO DE SOUZA | I24: 7773 | J24: TECNICO DE MANUTENCAO PI II | K24: 12.08.1 | L24: 26387 | M24: TIM MOVEL | N24: 09/04/2026 00:00:00 | Q24: PR | R24: SUL | S24: UMUARAMA | T24: ATIVO | U24: SAVEIRO | V24: R$ 0,00 | W24: MOVIDA | X24: samara.pereira@ondacom.com | Y24: 16/04/2026 11:28:29
A25: Atualizado | B25: 2786 | C25: TXJ7D53 | D25: HB20 | E25: LEVE | F25: 2026 | G25: 2025 | H25: JOAO PAULO FERREIRA MARIANO | I25: 7552 | J25: TECNICO DE SEGURANCA DO TRABALHO SR | K25: 99.67.8 | L25: 35001 | M25: ADMINISTRATIVO | Q25: SP | R25: SUDESTE | S25: SÃO PAULO | T25: ATIVO | U25: HB20 | V25: R$ 0,00 | W25: LOCALIZA | X25: 8989BRUNA RIBEIRO LIMA | Y25: 16/04/2026 10:34:30
A26: Atualizado | B26: 2785 | C26: UAS3B93 | D26: SAVEIRO | E26: UTILITARIO | F26: 2026 | G26: 2025 | H26: DORIVAL OLIVEIRA DA SILVA | I26: 9423 | J26: TECNICO DE MANUTENCAO PI I | K26: 12.08.1 | L26: 37133 | M26: TIM MOVEL | N26: 16/01/2026 01:00:00 | Q26: TO | R26: NORTE | S26: PALMAS | T26: ATIVO | U26: SAVEIRO | V26: R$ 0,00 | W26: MOVIDA | X26: elizabete.costa@ondacom.com | Y26: 16/04/2026 10:22:06
A27: Novo | B27: 2784 | C27: TYN9F83 | D27: FIORINO | E27: UTILITARIO | F27: 2026 | G27: 2025 | H27: - | I27: - | J27: - | N27: 15/04/2026 01:00:00 | Q27: TO | R27: NORTE | S27: PALMAS | T27: PATIO | U27: FIORINO | V27: R$ 0,00 | W27: LOCALIZA | X27: elizabete.costa@ondacom.com | Y27: 16/04/2026 10:09:49
A28: Atualizado | B28: 2783 | C28: UFV2J74 | D28: HILUX | E28: 4X4 | F28: 2026 | G28: 2025 | H28: FRANCISCO SILVESTRE PAES FILHO | I28: 9590 | J28: TECNICO DE MANUTENCAO PI I | K28: 12.08.1 | L28: 22020 | M28: TIM MOVEL | P28: 30 | Q28: MS | R28: CENTRO OESTE | S28: DOURADOS | T28: ATIVO | U28: HILUX | V28: R$ 0,00 | W28: MOVIDA | X28: leandro.onca@ondacom.com | Y28: 15/04/2026 23:06:19
A29: Atualizado | B29: 2782 | C29: UFD1H85 | D29: HILUX | E29: 4X4 | F29: 2026 | G29: 2025 | H29: GILVAN VIEIRA DOS SANTOS | I29: 9631 | J29: TECNICO DE MANUTENCAO PI I | K29: 12.08.1 | L29: 37133 | M29: TIM MOVEL | N29: 15/04/2026 01:00:00 | Q29: TO | R29: NORTE | S29: PALMAS | T29: ATIVO | U29: HILUX | V29: R$ 0,00 | W29: MOVIDA | X29: elizabete.costa@ondacom.com | Y29: 16/04/2026 10:14:25 | Z29: VEICULO 0KM
A30: Atualizado | B30: 2781 | C30: RNK0B88 | D30: MOBI | E30: LEVE | F30: 2025 | G30: 2025 | H30: ADRIANO ROBERTO RAMOS VLAXIO | I30: 9555 | J30: TECNICO DE MANUTENCAO PI III | K30: 12.08.1 | L30: 32017 | M30: TIM MOVEL | N30: 06/04/2026 01:00:00 | Q30: RO | R30: Norte | S30: PORTO VELHO | T30: ATIVO | U30: MOBI | V30: R$ 0,00 | W30: MOVIDA | X30: elizabete.costa@ondacom.com | Y30: 14/04/2026 18:56:12
A31: Atualizado | B31: 2779 | C31: IVH8D40 | D31: L200 | E31: 4X4 | F31: 2011 | G31: 2014 | H31: JOSIMAR CORREA | I31: 9275 | J31: TECNICO DE MANUTENCAO PI II | K31: 12.08.1 | L31: 31288 | M31: TIM MOVEL | N31: 14/04/2026 00:00:00 | Q31: RS | R31: SUL | S31: PORTO ALEGRE | T31: ATIVO | U31: L200 | V31: R$ 2.791,00 | W31: PARTICULAR | X31: samara.pereira@ondacom.com | Y31: 15/04/2026 15:51:16
A32: Atualizado | B32: 2778 | C32: MGR5E59 | D32: 207 | E32: LEVE | F32: 2010 | G32: 2009 | H32: FAYLON AFONSO BENEDITO | I32: 4337 | J32: SUPERVISOR DE MANUTENCAO I | K32: 12.07.5 | L32: 26001 | M32: TIM | N32: 13/04/2026 00:00:00 | Q32: PR | R32: SUL | S32: CURITIBA | T32: ATIVO | U32: 207 | V32: R$ 972,00 | W32: PARTICULAR | X32: samara.pereira@ondacom.com | Y32: 14/04/2026 10:02:23
A33: Atualizado | B33: 2777 | C33: AZR9B56 | D33: FOCUS | E33: LEVE | F33: 2025 | G33: 2015 | H33: JOSE OSNI DA SILVA BUENO | I33: 9756 | J33: SUPERVISOR DE MANUTENCAO III | K33: 17.07.5 | L33: 26002 | M33: LIGGA | N33: 13/04/2026 00:00:00 | Q33: PR | R33: SUL | S33: PONTA GROSSA | T33: ATIVO | U33: FOCUS | V33: R$ 972,00 | W33: PARTICULAR | X33: samara.pereira@ondacom.com | Y33: 13/04/2026 15:44:09
A34: Atualizado | B34: 2776 | C34: UAS0C65 | D34: SAVEIRO | E34: UTILITARIO | F34: 2026 | G34: 2025 | H34: CARLOS ALBERTO BERDACKI | I34: 9633 | J34: TECNICO DE MANUTENCAO PI I | K34: 12.08.5 | L34: 26001 | M34: TIM MOVEL | N34: 06/04/2026 00:00:00 | Q34: PR | R34: SUL | S34: CURITIBA | T34: ATIVO | U34: SAVEIRO | V34: R$ 0,00 | W34: MOVIDA | X34: samara.pereira@ondacom.com | Y34: 14/04/2026 15:41:10
A35: Atualizado | B35: 2775 | C35: UFB7I16 | D35: HILUX | E35: 4X4 | F35: 2026 | G35: 2025 | H35: JONE CASTRO FERREIRA | I35: 9470 | J35: TECNICO DE MANUTENCAO PI III | K35: 12.08.1 | L35: 32017 | M35: TIM MOVEL | N35: 09/04/2026 01:00:00 | Q35: RO | R35: Norte | S35: PORTO VELHO | T35: ATIVO | U35: HILUX | V35: R$ 0,00 | W35: MOVIDA | X35: elizabete.costa@ondacom.com | Y35: 12/04/2026 11:39:56
A36: Atualizado | B36: 2774 | C36: UAS3F96 | D36: SAVEIRO | E36: UTILITARIO | F36: 2026 | G36: 2025 | H36: DANIEL VINICIO MENEZES JORGE | I36: 9438 | J36: TECNICO DE MANUTENCAO PI I | K36: 12.08.1 | L36: 37133 | M36: TIM MOVEL | N36: 10/04/2026 01:00:00 | Q36: TO | R36: NORTE | S36: PALMAS | T36: ATIVO | U36: SAVEIRO | V36: R$ 0,00 | W36: MOVIDA | X36: elizabete.costa@ondacom.com | Y36: 12/04/2026 10:35:48
A37: Novo | B37: 2773 | C37: UAS4A43 | D37: SAVEIRO | E37: UTILITARIO | F37: 2026 | G37: 2025 | H37: - | I37: - | J37: - | N37: 10/04/2026 00:00:00 | O37: 10/04/2028 12:00:00 | Q37: GO | R37: CENTRO OESTE | S37: APARECIDA DE GOIANIA | T37: PATIO | U37: SAVEIRO | V37: R$ 0,00 | W37: MOVIDA | X37: leslye.ramos@ondacom.com | Y37: 10/04/2026 19:33:18 | Z37: OPERAÇÃO TIM
A38: Novo | B38: 2772 | C38: UAS4A37 | D38: SAVEIRO | E38: UTILITARIO | F38: 2026 | G38: 2025 | H38: - | I38: - | J38: - | N38: 10/04/2026 00:00:00 | O38: 10/04/2028 12:00:00 | Q38: GO | R38: CENTRO OESTE | S38: APARECIDA DE GOIANIA | T38: PATIO | U38: SAVEIRO | V38: R$ 0,00 | W38: MOVIDA | X38: leslye.ramos@ondacom.com | Y38: 10/04/2026 19:32:06 | Z38: OPERAÇÃO TIM
A39: Atualizado | B39: 2771 | C39: UAS3J33 | D39: SAVEIRO | E39: UTILITARIO | F39: 2026 | G39: 2025 | H39: CELIO PEREIRA DA SILVA JUNIOR | I39: 9457 | J39: TECNICO DE MANUTENCAO PI II | K39: 12.08.1 | L39: 19019 | M39: TIM MOVEL | N39: 10/04/2026 00:00:00 | O39: 10/04/2028 12:00:00 | Q39: GO | R39: CENTRO OESTE | S39: APARECIDA DE GOIANIA | T39: ATIVO | U39: SAVEIRO | V39: R$ 0,00 | W39: MOVIDA | X39: leslye.ramos@ondacom.com | Y39: 10/04/2026 19:50:30 | Z39: OPERAÇÃO TIM
A40: Atualizado | B40: 2770 | C40: UAS3H91 | D40: SAVEIRO | E40: UTILITARIO | F40: 2026 | G40: 2025 | H40: RAIMUNDO NONATO ALVES GOMES | I40: 9672 | J40: TECNICO DE MANUTENCAO PI III | K40: 12.08.1 | L40: 19019 | M40: TIM MOVEL | N40: 10/04/2026 00:00:00 | O40: 10/04/2028 12:00:00 | Q40: GO | R40: CENTRO OESTE | S40: APARECIDA DE GOIANIA | T40: ATIVO | U40: SAVEIRO | V40: R$ 0,00 | W40: MOVIDA | X40: leslye.ramos@ondacom.com | Y40: 10/04/2026 19:14:36 | Z40: OPERAÇÃO TIM
A41: Atualizado | B41: 2769 | C41: UAS4C03 | D41: SAVEIRO | E41: UTILITARIO | F41: 2026 | G41: 2025 | H41: DIJAIME DE JESUS BOMFIM | I41: 9591 | J41: TECNICO DE MANUTENCAO PI I | K41: 12.08.1 | L41: 19019 | M41: TIM MOVEL | N41: 10/04/2026 00:00:00 | O41: 10/04/2028 12:00:00 | Q41: GO | R41: CENTRO OESTE | S41: APARECIDA DE GOIANIA | T41: ATIVO | U41: SAVEIRO | V41: R$ 0,00 | W41: MOVIDA | X41: leslye.ramos@ondacom.com | Y41: 10/04/2026 18:27:03 | Z41: OPERAÇÃO TIM
A42: Atualizado | B42: 2768 | C42: UAS3J52 | D42: SAVEIRO | E42: UTILITARIO | F42: 2026 | G42: 2025 | H42: LUIS FERNANDO SILVA DA COSTA | I42: 9639 | J42: TECNICO DE MANUTENCAO PI II | K42: 12.08.1 | L42: 19019 | M42: TIM MOVEL | N42: 10/04/2026 00:00:00 | O42: 10/04/2028 12:00:00 | Q42: GO | R42: CENTRO OESTE | S42: APARECIDA DE GOIANIA | T42: ATIVO | U42: SAVEIRO | V42: R$ 0,00 | W42: MOVIDA | X42: leslye.ramos@ondacom.com | Y42: 10/04/2026 17:53:44 | Z42: OPERAÇÃO TIM
A43: Atualizado | B43: 2767 | C43: UAS3I78 | D43: SAVEIRO | E43: UTILITARIO | F43: 2026 | G43: 2025 | H43: JULIO DE OLIVEIRA | I43: 9661 | J43: TECNICO DE MANUTENCAO PI I | K43: 12.08.1 | L43: 37133 | M43: TIM MOVEL | N43: 10/04/2026 01:00:00 | Q43: TO | R43: NORTE | S43: PALMAS | T43: ATIVO | U43: SAVEIRO | V43: R$ 0,00 | W43: MOVIDA | X43: elizabete.costa@ondacom.com | Y43: 12/04/2026 10:22:49
A44: Atualizado | B44: 2766 | C44: UDG0C86 | D44: HILUX | E44: 4X4 | F44: 2026 | G44: 2025 | H44: MANUTENCAO PLANTA INTERNA TIM PORTO ALEGRE | I44: PO019 | J44: PARCEIRO | K44: 12.08.1 | L44: 31001 | M44: TIM MOVEL | N44: 03/04/2026 00:00:00 | Q44: RS | R44: SUL | S44: PORTO ALEGRE | T44: ATIVO | U44: HILUX | V44: R$ 0,00 | W44: MOVIDA | X44: samara.pereira@ondacom.com | Y44: 15/04/2026 17:42:25
A45: Atualizado | B45: 2765 | C45: UDI2H32 | D45: HILUX | E45: 4X4 | F45: 2026 | G45: 2026 | H45: GILSON ANTONIO DIAS | I45: 9515 | J45: TECNICO DE MANUTENCAO PI II | K45: 12.08.1 | L45: 21104 | M45: TIM MOVEL | N45: 10/04/2026 00:00:00 | O45: 10/04/2028 12:00:00 | Q45: MT | R45: Centro-Oeste | S45: JUINA | T45: ATIVO | U45: HILUX | V45: R$ 0,00 | W45: MOVIDA | X45: rafael.candido@ondacom.com | Y45: 10/04/2026 16:03:11
A46: Atualizado | B46: 2764 | C46: UFW0A98 | D46: HILUX | E46: 4X4 | F46: 2026 | G46: 2025 | H46: ARTUR ALBANO GAUER | I46: 4747 | J46: TECNICO DE MANUTENCAO PI I | K46: 12.08.1 | L46: 31271 | M46: TIM MOVEL | N46: 07/04/2026 00:00:00 | Q46: RS | R46: SUL | S46: PORTO ALEGRE | T46: ATIVO | U46: HILUX | V46: R$ 0,00 | W46: MOVIDA | X46: samara.pereira@ondacom.com | Y46: 10/04/2026 10:04:15
A47: Atualizado | B47: 2763 | C47: UAS4A50 | D47: SAVEIRO | E47: UTILITARIO | F47: 2026 | G47: 2025 | H47: FRANCISCO CHAGAS SOUZA | I47: 9455 | J47: ASSISTENTE TEC. DE MANUTENCAO DE PI II | K47: 12.08.1 | L47: 19019 | M47: TIM MOVEL | N47: 09/04/2026 00:00:00 | O47: 09/04/2028 12:00:00 | Q47: GO | R47: CENTRO OESTE | S47: APARECIDA DE GOIANIA | T47: ATIVO | U47: SAVEIRO | V47: R$ 0,00 | W47: MOVIDA | X47: leslye.ramos@ondacom.com | Y47: 10/04/2026 09:18:01 | Z47: OPERACÃO TIM
A48: Atualizado | B48: 2762 | C48: UAS3G75 | D48: SAVEIRO | E48: UTILITARIO | F48: 2026 | G48: 2025 | H48: ROGERIO DA SILVA SANTOS | I48: 9754 | J48: TECNICO DE MANUTENCAO PI III | K48: 12.08.1 | L48: 19048 | M48: TIM MOVEL | N48: 09/04/2026 00:00:00 | O48: 09/04/2028 12:00:00 | Q48: GO | R48: CENTRO OESTE | S48: APARECIDA DE GOIANIA | T48: ATIVO | U48: SAVEIRO | V48: R$ 0,00 | W48: MOVIDA | X48: leslye.ramos@ondacom.com | Y48: 09/04/2026 20:35:25 | Z48: OPERAÇÃO TIM
A49: Atualizado | B49: 2761 | C49: UAS3G19 | D49: SAVEIRO | E49: UTILITARIO | F49: 2026 | G49: 2025 | H49: KERVEN ROBERT FELIX REIS | I49: 9537 | J49: ESPECIALISTA OPERACIONAL DE PI I | K49: 12.08.1 | L49: 19019 | M49: TIM MOVEL | N49: 09/04/2026 00:00:00 | O49: 09/04/2028 12:00:00 | Q49: GO | R49: CENTRO OESTE | S49: APARECIDA DE GOIANIA | T49: ATIVO | U49: SAVEIRO | V49: R$ 0,00 | W49: MOVIDA | X49: leslye.ramos@ondacom.com | Y49: 09/04/2026 20:41:20 | Z49: OPERAÇÃO TIM
A50: Atualizado | B50: 2760 | C50: UDV9B75 | D50: HILUX | E50: 4X4 | F50: 2026 | G50: 2025 | H50: MANUTENCAO PLANTA INTERNA TIM SAO JOSE | I50: PO029 | J50: PARCEIRO | K50: 12.08.5 | L50: 34248 | M50: TIM MOVEL | N50: 03/04/2026 00:00:00 | Q50: SC | R50: SUL | S50: SÃO JOSE | T50: ATIVO | U50: HILUX | V50: R$ 0,00 | W50: MOVIDA | X50: samara.pereira@ondacom.com | Y50: 09/04/2026 16:45:02
A51: Novo | B51: 2759 | C51: TYN9F68 | D51: FIORINO | E51: UTILITARIO | F51: 2026 | G51: 2026 | H51: - | I51: - | J51: - | Q51: MS | R51: CENTRO OESTE | S51: CAMPO GRANDE | T51: PATIO | U51: FIORINO | V51: R$ 0,00 | W51: LOCALIZA | X51: leandro.onca@ondacom.com | Y51: 09/04/2026 13:05:47
A52: Atualizado | B52: 2758 | C52: TYN9F76 | D52: FIORINO | E52: UTILITARIO | F52: 2026 | G52: 2026 | H52: NEUMARQUES WESLEM ALVES PEREIRA | I52: 9467 | J52: ASSISTENTE TEC. DE MANUTENCAO DE FO I | K52: 12.07.1 | L52: 22020 | M52: TIM MOVEL | Q52: MS | R52: CENTRO OESTE | S52: CAMPO GRANDE | T52: ATIVO | U52: FIORINO | V52: R$ 0,00 | W52: LOCALIZA | X52: leandro.onca@ondacom.com | Y52: 09/04/2026 23:27:09
A53: Atualizado | B53: 2757 | C53: UAS5G62 | D53: SAVEIRO | E53: UTILITARIO | F53: 2026 | G53: 2025 | H53: FABIANO DA SILVA PRADO | I53: 9513 | J53: TECNICO DE MANUTENCAO PI I | K53: 12.08.1 | L53: 22020 | M53: TIM MOVEL | Q53: MS | R53: CENTRO OESTE | S53: CAMPO GRANDE | T53: ATIVO | U53: SAVEIRO | V53: R$ 0,00 | W53: MOVIDA | X53: leandro.onca@ondacom.com | Y53: 09/04/2026 23:08:42
A54: Atualizado | B54: 2756 | C54: UAS3I70 | D54: SAVEIRO | E54: UTILITARIO | F54: 2026 | G54: 2025 | H54: HENRIQUE ABINADABE OLMEDO DE LIMA | I54: 9540 | J54: TECNICO DE MANUTENCAO PI I | K54: 12.08.1 | L54: 22020 | M54: TIM MOVEL | Q54: MS | R54: CENTRO OESTE | S54: CAMPO GRANDE | T54: ATIVO | U54: SAVEIRO | V54: R$ 0,00 | W54: MOVIDA | X54: leandro.onca@ondacom.com | Y54: 09/04/2026 22:59:33
A55: Atualizado | B55: 2755 | C55: UAS3C80 | D55: SAVEIRO | E55: UTILITARIO | F55: 2026 | G55: 2025 | H55: REGINALDO PEREIRA DOS REIS | I55: 9581 | J55: TECNICO DE MANUTENCAO PI III | K55: 12.08.1 | L55: 19019 | M55: TIM MOVEL | N55: 08/04/2026 00:00:00 | O55: 08/04/2028 12:00:00 | Q55: GO | R55: CENTRO OESTE | S55: APARECIDA DE GOIANIA | T55: ATIVO | U55: SAVEIRO | V55: R$ 0,00 | W55: MOVIDA | X55: leslye.ramos@ondacom.com | Y55: 09/04/2026 11:32:32 | Z55: OPERAÇÃO TIM
A56: Atualizado | B56: 2754 | C56: UAS4A28 | D56: SAVEIRO | E56: UTILITARIO | F56: 2026 | G56: 2025 | H56: FABIO RIBEIRO DE SOUZA SENA | I56: 9727 | J56: ESPECIALISTA OPERACIONAL DE PI III | K56: 12.08.1 | L56: 19019 | M56: TIM MOVEL | N56: 08/04/2026 00:00:00 | O56: 08/04/2028 12:00:00 | Q56: GO | R56: CENTRO OESTE | S56: APARECIDA DE GOIANIA | T56: ATIVO | U56: SAVEIRO | V56: R$ 0,00 | W56: MOVIDA | X56: leslye.ramos@ondacom.com | Y56: 09/04/2026 09:36:18 | Z56: OPERAÇÃO TIM
A57: Novo | B57: 2753 | C57: TDJ6H97 | D57: POLO | E57: LEVE | F57: 2025 | G57: 2024 | H57: - | I57: - | J57: - | N57: 08/04/2026 00:00:00 | Q57: MG | R57: SUDESTE | S57: UBERLANDIA | T57: PATIO | U57: POLO | V57: R$ 0,00 | W57: LOCALIZA | X57: leslye.ramos@ondacom.com | Y57: 08/04/2026 20:14:45 | Z57: RENT A CAR
A58: Atualizado | B58: 2752 | C58: UAS3F33 | D58: SAVEIRO | E58: UTILITARIO | F58: 2025 | G58: 2026 | H58: VALDERI PEREIRA DA SILVA | I58: 9755 | J58: TECNICO DE MANUTENCAO PI IV | K58: 12.08.1 | L58: 19019 | M58: TIM MOVEL | N58: 08/04/2026 00:00:00 | O58: 08/04/2028 12:00:00 | Q58: GO | R58: CENTRO OESTE | S58: APARECIDA DE GOIANIA | T58: ATIVO | U58: SAVEIRO | V58: R$ 0,00 | W58: MOVIDA | X58: leslye.ramos@ondacom.com | Y58: 08/04/2026 19:24:43 | Z58: OPERAÇÃO TIM
A59: Atualizado | B59: 2751 | C59: TYN9F81 | D59: FIORINO | E59: UTILITARIO | F59: 2026 | G59: 2026 | H59: DANIEL FERNANDES FERREIRA DE SOUZA | I59: 9725 | J59: ASSISTENTE TEC. DE MANUTENCAO DE FO III | K59: 12.07.1 | L59: 21104 | M59: TIM MOVEL | N59: 08/04/2026 00:00:00 | O59: 08/04/2028 12:00:00 | Q59: MT | R59: CENTRO OESTE | S59: RONDONÓPOLIS | T59: ATIVO | U59: FIORINO | V59: R$ 0,00 | W59: LOCALIZA | X59: vitor.silva@ondacom.com | Y59: 09/04/2026 12:05:04
A60: Atualizado | B60: 2750 | C60: UEI1J72 | D60: HILUX | E60: 4X4 | F60: 2026 | G60: 2025 | H60: FABRICIO VOSS KLEMTZ | I60: 4349 | J60: TECNICO DE MANUTENCAO PI III | K60: 12.08.1 | L60: 26006 | M60: TIM MOVEL | N60: 02/04/2026 00:00:00 | Q60: PR | R60: SUL | S60: GUARAPUAVA | T60: ATIVO | U60: HILUX | V60: R$ 0,00 | W60: MOVIDA | X60: samara.pereira@ondacom.com | Y60: 15/04/2026 14:53:19
A61: Atualizado | B61: 2749 | C61: UAS3D46 | D61: SAVEIRO | E61: UTILITARIO | F61: 2026 | G61: 2025 | H61: HELDER BOMFIM RODRIGUES COSTA | I61: 9772 | J61: TECNICO DE MANUTENCAO PI I | K61: 12.08.1 | L61: 37133 | M61: TIM MOVEL | N61: 08/04/2026 01:00:00 | Q61: TO | R61: NORTE | S61: PALMAS | T61: ATIVO | U61: SAVEIRO | V61: R$ 0,00 | W61: MOVIDA | X61: elizabete.costa@ondacom.com | Y61: 14/04/2026 16:21:01 | Z61: sem avarias
A62: Atualizado | B62: 2748 | C62: UFR6B34 | D62: HILUX | E62: 4X4 | F62: 2026 | G62: 2025 | H62: ODIRLEI ROGERIO DA SILVA | I62: 4334 | J62: TECNICO DE MANUTENCAO PI III | K62: 12.08.1 | L62: 26158 | M62: TIM MOVEL | Q62: PR | R62: SUL | S62: IRATI | T62: ATIVO | U62: HILUX | V62: R$ 0,00 | W62: MOVIDA | X62: samara.pereira@ondacom.com | Y62: 08/04/2026 14:55:40
A63: Atualizado | B63: 2747 | C63: UFB0C79 | D63: HILUX | E63: 4X4 | F63: 2026 | G63: 2025 | H63: MATHEUS VINICIUS DA SILVA GOMES | I63: 4382 | J63: ESPECIALISTA OPERACIONAL DE PI II | K63: 12.08.1 | L63: 26027 | M63: TIM MOVEL | N63: 02/04/2026 00:00:00 | Q63: PR | R63: SUL | S63: MARINGÁ | T63: ATIVO | U63: HILUX | V63: R$ 0,00 | W63: MOVIDA | X63: samara.pereira@ondacom.com | Y63: 07/04/2026 09:34:50
A64: Atualizado | B64: 2746 | C64: QSV4J67 | D64: HILUX | E64: 4X4 | F64: 2025 | G64: 2026 | H64: RONISCLEY JOSE PEREIRA | I64: 9583 | J64: TECNICO DE MANUTENCAO PI III | K64: 12.08.1 | L64: 19019 | M64: TIM MOVEL | N64: 27/03/2026 17:00:00 | O64: 27/03/2030 12:00:00 | Q64: GO | R64: CENTRO OESTE | S64: APARECIDA DE GOIANIA | T64: ATIVO | U64: HILUX | V64: R$ 0,00 | W64: MOVIDA | X64: leslye.ramos@ondacom.com | Y64: 09/04/2026 10:49:49 | Z64: OPERAÇÃO TIM
A65: Novo | B65: 2745 | C65: GUR0009 | D65: B4T 13000E | E65: GERADOR | F65: 2026 | G65: 2026 | H65: - | I65: - | J65: - | N65: 01/04/2026 00:00:00 | O65: 01/04/2030 12:00:00 | Q65: TO | R65: NORDESTE | S65: PALMAS | T65: PATIO | U65: B4T 13000E | V65: R$ 0,00 | W65: EQUIPAMENTO | X65: leslye.ramos@ondacom.com | Y65: 06/04/2026 19:16:42 | Z65: GERADOR ESTACIONARIO TIM
A66: Novo | B66: 2744 | C66: ARN0009 | D66: B4T 13000E | E66: GERADOR | F66: 2026 | G66: 2026 | H66: - | I66: - | J66: - | N66: 01/04/2026 00:00:00 | O66: 01/04/2030 12:00:00 | Q66: TO | R66: NORDESTE | S66: PALMAS | T66: PATIO | U66: B4T 13000E | V66: R$ 0,00 | W66: EQUIPAMENTO | X66: leslye.ramos@ondacom.com | Y66: 06/04/2026 19:15:37 | Z66: GERADOR ESTACIONARIO TIM
A67: Novo | B67: 2743 | C67: TGG0001 | D67: B4T 13000E | E67: GERADOR | F67: 2026 | G67: 2026 | H67: - | I67: - | J67: - | N67: 01/04/2026 00:00:00 | O67: 01/04/2030 12:00:00 | Q67: TO | R67: NORDESTE | S67: PALMAS | T67: PATIO | U67: B4T 13000E | V67: R$ 0,00 | W67: EQUIPAMENTO | X67: leslye.ramos@ondacom.com | Y67: 06/04/2026 19:14:31 | Z67: GERADOR ESTACIONARIO TIM
A68: Novo | B68: 2742 | C68: PXC0006 | D68: B4T 13000E | E68: GERADOR | F68: 2026 | G68: 2026 | H68: - | I68: - | J68: - | N68: 01/04/2026 00:00:00 | O68: 01/04/2030 12:00:00 | Q68: TO | R68: NORDESTE | S68: PALMAS | T68: PATIO | U68: B4T 13000E | V68: R$ 0,00 | W68: EQUIPAMENTO | X68: leslye.ramos@ondacom.com | Y68: 06/04/2026 19:13:41 | Z68: GERADOR ESTACIONARIO TIM
A69: Novo | B69: 2741 | C69: PMJ0042 | D69: B4T 13000E | E69: GERADOR | F69: 2026 | G69: 2026 | H69: - | I69: - | J69: - | N69: 01/04/2026 00:00:00 | O69: 01/04/2030 12:00:00 | Q69: TO | R69: NORDESTE | S69: PALMAS | T69: PATIO | U69: B4T 13000E | V69: R$ 0,00 | W69: EQUIPAMENTO | X69: leslye.ramos@ondacom.com | Y69: 06/04/2026 19:01:07 | Z69: GERADOR ESTACIONARIO TIM
A70: Novo | B70: 2740 | C70: MRR0002 | D70: B4T 13000E | E70: GERADOR | F70: 2026 | G70: 2026 | H70: - | I70: - | J70: - | N70: 01/04/2026 00:00:00 | O70: 01/04/2030 12:00:00 | Q70: TO | R70: NORDESTE | S70: PALMAS | T70: PATIO | U70: B4T 13000E | V70: R$ 0,00 | W70: EQUIPAMENTO | X70: leslye.ramos@ondacom.com | Y70: 06/04/2026 18:59:33 | Z70: GERADOR ESTACIONARIO TIM
A71: Novo | B71: 2739 | C71: GUI0002 | D71: B4T 13000E | E71: GERADOR | F71: 2026 | G71: 2026 | H71: - | I71: - | J71: - | N71: 01/04/2026 00:00:00 | O71: 01/04/2030 12:00:00 | Q71: TO | R71: NORDESTE | S71: PALMAS | T71: PATIO | U71: B4T 13000E | V71: R$ 0,00 | W71: EQUIPAMENTO | X71: leslye.ramos@ondacom.com | Y71: 06/04/2026 18:58:33 | Z71: GERADOR ESTACIONARIO TIM
A72: Novo | B72: 2738 | C72: DIS0001 | D72: B4T 13000E | E72: GERADOR | F72: 2026 | G72: 2026 | H72: - | I72: - | J72: - | N72: 01/04/2026 00:00:00 | O72: 01/04/2030 12:00:00 | Q72: TO | R72: NORDESTE | S72: PALMAS | T72: PATIO | U72: B4T 13000E | V72: R$ 0,00 | W72: EQUIPAMENTO | X72: leslye.ramos@ondacom.com | Y72: 06/04/2026 18:57:33 | Z72: GERADOR ESTACIONARIO TIM
A73: Novo | B73: 2737 | C73: CGO0002 | D73: B4T 13000E | E73: GERADOR | F73: 2026 | G73: 2026 | H73: - | I73: - | J73: - | N73: 01/04/2026 00:00:00 | O73: 01/04/2030 12:00:00 | Q73: TO | R73: NORDESTE | S73: PALMAS | T73: PATIO | U73: B4T 13000E | V73: R$ 0,00 | W73: EQUIPAMENTO | X73: leslye.ramos@ondacom.com | Y73: 06/04/2026 18:54:32 | Z73: GERADOR ESTACIONARIO TIM
A74: Novo | B74: 2736 | C74: AVO0002 | D74: B4T 13000E | E74: GERADOR | F74: 2026 | G74: 2026 | H74: - | I74: - | J74: - | N74: 01/04/2026 00:00:00 | O74: 01/04/2030 12:00:00 | Q74: TO | R74: NORDESTE | S74: PALMAS | T74: PATIO | U74: B4T 13000E | V74: R$ 0,00 | W74: EQUIPAMENTO | X74: leslye.ramos@ondacom.com | Y74: 06/04/2026 18:42:01
A75: Novo | B75: 2735 | C75: CWL0006 | D75: B4T 13000E | E75: GERADOR | F75: 2026 | G75: 2026 | H75: - | I75: - | J75: - | N75: 01/04/2026 00:00:00 | O75: 01/04/2030 12:00:00 | Q75: RO | R75: Norte | S75: PORTO VELHO | T75: PATIO | U75: B4T 13000E | V75: R$ 0,00 | W75: EQUIPAMENTO | X75: leslye.ramos@ondacom.com | Y75: 06/04/2026 18:39:55 | Z75: GERADOR ESTACIONARIO TIM
A76: Novo | B76: 2734 | C76: CBA0036 | D76: B4T 13000E | E76: GERADOR | F76: 2026 | G76: 2026 | H76: - | I76: - | J76: - | N76: 01/04/2026 00:00:00 | O76: 01/04/2030 12:00:00 | Q76: MT | R76: CENTRO OESTE | S76: RONDONÓPOLIS | T76: PATIO | U76: B4T 13000E | V76: R$ 0,00 | W76: EQUIPAMENTO | X76: leslye.ramos@ondacom.com | Y76: 06/04/2026 18:26:14 | Z76: GERADOR ESTACIONARIO TIM
A77: Novo | B77: 2733 | C77: ROI0009 | D77: B4T 13000E | E77: GERADOR | F77: 2026 | G77: 2026 | H77: - | I77: - | J77: - | N77: 01/04/2026 00:00:00 | O77: 01/04/2030 12:00:00 | Q77: MT | R77: CENTRO OESTE | S77: RONDONÓPOLIS | T77: PATIO | U77: B4T 13000E | V77: R$ 0,00 | W77: EQUIPAMENTO | X77: leslye.ramos@ondacom.com | Y77: 06/04/2026 18:24:27 | Z77: GERADOR ESTACIONARIO TIM
A78: Novo | B78: 2732 | C78: PXP0001 | D78: B4T 13000E | E78: GERADOR | F78: 2026 | G78: 2026 | H78: - | I78: - | J78: - | N78: 01/04/2026 00:00:00 | O78: 01/04/2030 12:00:00 | Q78: MT | R78: CENTRO OESTE | S78: RONDONÓPOLIS | T78: PATIO | U78: B4T 13000E | V78: R$ 0,00 | W78: EQUIPAMENTO | X78: leslye.ramos@ondacom.com | Y78: 06/04/2026 18:23:26 | Z78: GERADOR ESTACIONARIO TIM
A79: Novo | B79: 2731 | C79: PCK0002 | D79: B4T 13000E | E79: GERADOR | F79: 2026 | G79: 2026 | H79: - | I79: - | J79: - | N79: 01/04/2026 00:00:00 | O79: 01/04/2030 12:00:00 | Q79: MT | R79: CENTRO OESTE | S79: RONDONÓPOLIS | T79: PATIO | U79: B4T 13000E | V79: R$ 0,00 | W79: EQUIPAMENTO | X79: leslye.ramos@ondacom.com | Y79: 06/04/2026 18:21:53 | Z79: GERADOR ESTACIONARIO TIM
A80: Novo | B80: 2730 | C80: JCR0003 | D80: B4T 13000E | E80: GERADOR | F80: 2026 | G80: 2026 | H80: - | I80: - | J80: - | N80: 01/04/2026 00:00:00 | O80: 01/04/2030 12:00:00 | Q80: MT | R80: CENTRO OESTE | S80: RONDONÓPOLIS | T80: PATIO | U80: B4T 13000E | V80: R$ 0,00 | W80: EQUIPAMENTO | X80: leslye.ramos@ondacom.com | Y80: 06/04/2026 18:20:44 | Z80: GERADOR ESTACIONARIO TIM
A81: Atualizado | B81: 2729 | C81: UAS3B58 | D81: SAVEIRO | E81: UTILITARIO | F81: 2025 | G81: 2026 | H81: YGOR ESPINDOLA DUARTE | I81: 9594 | J81: TECNICO DE MANUTENCAO PI I | K81: 12.08.1 | L81: 22032 | M81: TIM MOVEL | N81: 06/04/2026 00:00:00 | O81: 06/04/2028 12:00:00 | Q81: MS | R81: CENTRO OESTE | S81: CAMPO GRANDE | T81: ATIVO | U81: SAVEIRO | V81: R$ 0,00 | W81: MOVIDA | X81: leandro.onca@ondacom.com | Y81: 07/04/2026 08:47:05
A82: Novo | B82: 2728 | C82: UAS4B28 | D82: SAVEIRO | E82: UTILITARIO | F82: 2025 | G82: 2026 | H82: - | I82: - | J82: - | N82: 06/04/2026 00:00:00 | O82: 06/04/2028 12:00:00 | Q82: MT | R82: Centro-Oeste | S82: CUIABA | T82: PATIO | U82: SAVEIRO | V82: R$ 0,00 | W82: MOVIDA | X82: vitor.silva@ondacom.com | Y82: 06/04/2026 18:16:34
A83: Novo | B83: 2727 | C83: CZV0002 | D83: B4T 13000E | E83: GERADOR | F83: 2026 | G83: 2026 | H83: - | I83: - | J83: - | N83: 01/04/2026 00:00:00 | O83: 01/04/2030 12:00:00 | Q83: MT | R83: CENTRO OESTE | S83: RONDONÓPOLIS | T83: PATIO | U83: B4T 13000E | V83: R$ 0,00 | W83: EQUIPAMENTO | X83: leslye.ramos@ondacom.com | Y83: 06/04/2026 17:59:49 | Z83: GERADOR ESTACIONARIO TIM
A84: Novo | B84: 2726 | C84: CBA0040 | D84: B4T 13000E | E84: GERADOR | F84: 2026 | G84: 2026 | H84: - | I84: - | J84: - | N84: 01/04/2026 00:00:00 | O84: 01/04/2030 12:00:00 | Q84: MT | R84: CENTRO OESTE | S84: RONDONÓPOLIS | T84: PATIO | U84: B4T 13000E | V84: R$ 0,00 | W84: EQUIPAMENTO | X84: leslye.ramos@ondacom.com | Y84: 06/04/2026 17:58:20 | Z84: GERADOR ESTACIONARIO TIM
A85: Novo | B85: 2725 | C85: ALU0001 | D85: B4T 13000E | E85: GERADOR | F85: 2026 | G85: 2026 | H85: - | I85: - | J85: - | N85: 01/04/2026 00:00:00 | O85: 01/04/2030 12:00:00 | Q85: MT | R85: CENTRO OESTE | S85: RONDONÓPOLIS | T85: PATIO | U85: B4T 13000E | V85: R$ 0,00 | W85: EQUIPAMENTO | X85: leslye.ramos@ondacom.com | Y85: 06/04/2026 17:57:07 | Z85: GERADOR ESTACIONARIO TIM
A86: Novo | B86: 2724 | C86: PDG0001 | D86: B4T 13000E | E86: GERADOR | F86: 2026 | G86: 2026 | H86: - | I86: - | J86: - | Q86: MS | R86: CENTRO OESTE | S86: CAMPO GRANDE | T86: PATIO | U86: B4T 13000E | V86: R$ 0,00 | W86: EQUIPAMENTO | X86: leslye.ramos@ondacom.com | Y86: 06/04/2026 17:53:53 | Z86: GERADOR ESTACIONARIO TIM
A87: Novo | B87: 2723 | C87: SYW0001 | D87: B4T 13000E | E87: GERADOR | F87: 2026 | G87: 2026 | H87: - | I87: - | J87: - | N87: 01/04/2026 00:00:00 | O87: 01/04/2030 12:00:00 | Q87: MS | R87: CENTRO OESTE | S87: CAMPO GRANDE | T87: PATIO | U87: B4T 13000E | V87: R$ 0,00 | W87: EQUIPAMENTO | X87: leslye.ramos@ondacom.com | Y87: 06/04/2026 17:52:26 | Z87: GERADOR ESTACIONARIO TIM
A88: Novo | B88: 2722 | C88: RVG0001 | D88: B4T 13000E | E88: GERADOR | F88: 2026 | G88: 2026 | H88: - | I88: - | J88: - | N88: 01/04/2026 00:00:00 | O88: 01/04/2030 12:00:00 | Q88: MS | R88: CENTRO OESTE | S88: CAMPO GRANDE | T88: PATIO | U88: B4T 13000E | V88: R$ 0,00 | W88: EQUIPAMENTO | X88: leslye.ramos@ondacom.com | Y88: 06/04/2026 17:51:18 | Z88: GERADOR ESTACIONARIO TIM
A89: Novo | B89: 2721 | C89: RBH0001 | D89: B4T 13000E | E89: GERADOR | F89: 2026 | G89: 2026 | H89: - | I89: - | J89: - | N89: 01/04/2026 00:00:00 | O89: 01/04/2030 12:00:00 | Q89: MS | R89: CENTRO OESTE | S89: CAMPO GRANDE | T89: PATIO | U89: B4T 13000E | V89: R$ 0,00 | W89: EQUIPAMENTO | X89: leslye.ramos@ondacom.com | Y89: 06/04/2026 17:50:19 | Z89: GERADOR ESTACIONARIO TIM
A90: Atualizado | B90: 2720 | C90: NAA0003 | D90: B4T 13000E | E90: GERADOR | F90: 2026 | G90: 2026 | H90: - | I90: - | J90: - | N90: 01/04/2026 00:00:00 | O90: 01/04/2030 12:00:00 | Q90: MS | R90: CENTRO OESTE | S90: CAMPO GRANDE | T90: PATIO | U90: B4T 13000E | V90: R$ 0,00 | W90: EQUIPAMENTO | X90: leslye.ramos@ondacom.com | Y90: 06/04/2026 17:48:36 | Z90: GERADOR ESTACIONARIO TIM
A91: Atualizado | B91: 2719 | C91: IQR0001 | D91: B4T 13000E | E91: GERADOR | F91: 2026 | G91: 2026 | H91: - | I91: - | J91: - | N91: 01/04/2026 00:00:00 | O91: 01/04/2030 12:00:00 | Q91: MS | R91: CENTRO OESTE | S91: CAMPO GRANDE | T91: PATIO | U91: B4T 13000E | V91: R$ 0,00 | W91: EQUIPAMENTO | X91: leslye.ramos@ondacom.com | Y91: 06/04/2026 17:47:54 | Z91: GERADOR ESTACIONARIO TIM
A92: Atualizado | B92: 2718 | C92: DOS0002 | D92: B4T 13000E | E92: GERADOR | F92: 2026 | G92: 2026 | H92: - | I92: - | J92: - | N92: 01/04/2026 00:00:00 | O92: 01/04/2030 12:00:00 | Q92: MS | R92: CENTRO OESTE | S92: CAMPO GRANDE | T92: PATIO | U92: B4T 13000E | V92: R$ 0,00 | W92: EQUIPAMENTO | X92: leslye.ramos@ondacom.com | Y92: 06/04/2026 17:47:25 | Z92: GERADOR ESTACIONARIO TIM
A93: Atualizado | B93: 2717 | C93: BND0001 | D93: B4T 13000E | E93: GERADOR | F93: 2026 | G93: 2026 | H93: - | I93: - | J93: - | N93: 01/04/2026 00:00:00 | O93: 01/04/2030 12:00:00 | Q93: MS | R93: CENTRO OESTE | S93: CAMPO GRANDE | T93: PATIO | U93: B4T 13000E | V93: R$ 0,00 | W93: EQUIPAMENTO | X93: leslye.ramos@ondacom.com | Y93: 06/04/2026 17:46:55 | Z93: GERADO ESTACIONARIO TIM
A94: Novo | B94: 2716 | C94: URC0004 | D94: B4T 13000E | E94: GERADOR | F94: 2026 | G94: 2026 | H94: - | I94: - | J94: - | N94: 01/04/2026 00:00:00 | O94: 01/04/2030 12:00:00 | Q94: GO | R94: CENTRO OESTE | S94: APARECIDA DE GOIANIA | T94: PATIO | U94: B4T 13000E | V94: R$ 0,00 | W94: EQUIPAMENTO | X94: leslye.ramos@ondacom.com | Y94: 06/04/2026 17:40:45 | Z94: GERADOR ESTACIONARIO TIM
A95: Novo | B95: 2715 | C95: RVD0007 | D95: B4T 13000E | E95: GERADOR | F95: 2026 | G95: 2026 | H95: - | I95: - | J95: - | N95: 01/04/2026 00:00:00 | O95: 01/04/2030 12:00:00 | Q95: GO | R95: CENTRO OESTE | S95: APARECIDA DE GOIANIA | T95: PATIO | U95: B4T 13000E | V95: R$ 0,00 | W95: EQUIPAMENTO | X95: leslye.ramos@ondacom.com | Y95: 06/04/2026 17:38:26 | Z95: GERADOR ESTACIONARIO TIM
A96: Novo | B96: 2714 | C96: PGT0005 | D96: B4T 13000E | E96: GERADOR | F96: 2026 | G96: 2026 | H96: - | I96: - | J96: - | N96: 01/04/2026 00:00:00 | O96: 01/04/2030 12:00:00 | Q96: GO | R96: CENTRO OESTE | S96: APARECIDA DE GOIANIA | T96: PATIO | U96: B4T 13000E | V96: R$ 0,00 | W96: EQUIPAMENTO | X96: leslye.ramos@ondacom.com | Y96: 06/04/2026 17:37:10 | Z96: GERADOR ESTACIONARIO TIM
A97: Novo | B97: 2713 | C97: PEX0001 | D97: B4T 13000E | E97: GERADOR | F97: 2026 | G97: 2026 | H97: - | I97: - | J97: - | N97: 01/04/2026 00:00:00 | O97: 01/04/2030 12:00:00 | Q97: GO | R97: CENTRO OESTE | S97: APARECIDA DE GOIANIA | T97: PATIO | U97: B4T 13000E | V97: R$ 0,00 | W97: EQUIPAMENTO | X97: leslye.ramos@ondacom.com | Y97: 06/04/2026 17:19:05 | Z97: GERADOR ESTACIONARIO TIM
A98: Novo | B98: 2712 | C98: PBN0005 | D98: B4T 13000E | E98: GERADOR | F98: 2026 | G98: 2026 | H98: - | I98: - | J98: - | N98: 01/04/2026 00:00:00 | O98: 01/04/2030 12:00:00 | Q98: GO | R98: CENTRO OESTE | S98: APARECIDA DE GOIANIA | T98: PATIO | U98: B4T 13000E | V98: R$ 0,00 | W98: EQUIPAMENTO | X98: leslye.ramos@ondacom.com | Y98: 06/04/2026 17:11:15 | Z98: GERADOR ESTACIONARIO TIM
... A105: Novo | B105: 2705 | C105: BSA0166 | D105: B4T 13000E | E105: GERADOR | F105: 2026 | G105: 2026 | H105: - | I105: - | J105: - | N105: 01/04/2026 00:00:00 | O105: 01/04/2030 12:00:00 | Q105: DF | R105: CENTRO OESTE | S105: BRASILIA | T105: PATIO | U105: B4T 13000E | V105: R$ 0,00 | W105: PARTICULAR | X105: leslye.ramos@ondacom.com | Y105: 06/04/2026 15:45:00 | Z105: GERADOR ESTACIONARIO TIM
A106: Atualizado | B106: 2704 | C106: UFY9E38 | D106: HILUX | E106: 4X4 | F106: 2026 | G106: 2025 | H106: ALVARO VINICIUS RIBEIRO DORIA | I106: 4426 | J106: ESPECIALISTA OPERACIONAL DE PI II | K106: 12.08.1 | L106: 26001 | M106: TIM MOVEL | N106: 02/04/2026 00:00:00 | Q106: PR | R106: SUL | S106: CURITIBA | T106: ATIVO | U106: HILUX | V106: R$ 0,00 | W106: MOVIDA | X106: samara.pereira@ondacom.com | Y106: 06/04/2026 11:34:00
...

Sheet BASE_LOCADORAS
A1: LOCADORA | B1: PLACA | C1: MODELO | D1: CATEGORIA | E1: INICIO DE CONTRATO | F1: FIM DE CONTRATO | G1: VALOR
A2: LOCALIZA | B2: FJO8H12 | C2: SAVEIRO ROBUST 1.6 8V TOTAL FLEX 2P C/AR | E2: 15/12/2022 | F2: 25/11/2025 | G2: 2462.14
A3: LOCALIZA | B3: EUT4G92 | C3: SAVEIRO ROBUST 1.6 8V TOTAL FLEX 2P C/AR | E3: 13/12/2022 | F3: 25/11/2025 | G3: 2462.14
A4: LOCALIZA | B4: FLC7G24 | C4: SAVEIRO ROBUST 1.6 8V TOTAL FLEX 2P C/AR | E4: 19/12/2022 | F4: 25/11/2025 | G4: 2449.14
A5: LOCALIZA | B5: EDI4I76 | C5: SAVEIRO ROBUST 1.6 8V TOTAL FLEX 2P C/AR | E5: 13/12/2022 | F5: 25/11/2025 | G5: 2462.14
A6: LOCALIZA | B6: EHN2I96 | C6: SAVEIRO ROBUST 1.6 8V TOTAL FLEX 2P C/AR | E6: 13/12/2022 | F6: 25/11/2025 | G6: 2462.14
A7: LOCALIZA | B7: EWG5E81 | C7: SAVEIRO ROBUST 1.6 8V TOTAL FLEX 2P C/AR | E7: 13/12/2022 | F7: 25/11/2025 | G7: 2462.14
A8: LOCALIZA | B8: EXH5C42 | C8: SAVEIRO ROBUST 1.6 8V TOTAL FLEX 2P C/AR | E8: 13/12/2022 | F8: 25/11/2025 | G8: 2462.14
A9: LOCALIZA | B9: EAR8I71 | C9: SAVEIRO ROBUST 1.6 8V TOTAL FLEX 2P C/AR | E9: 13/12/2022 | F9: 25/11/2025 | G9: 2462.14
A10: LOCALIZA | B10: EJX8H36 | C10: SAVEIRO ROBUST 1.6 8V TOTAL FLEX 2P C/AR | E10: 15/12/2022 | F10: 25/11/2025 | G10: 2462.14
A11: LOCALIZA | B11: EKU9J36 | C11: SAVEIRO ROBUST 1.6 8V TOTAL FLEX 2P C/AR | E11: 15/12/2022 | F11: 25/11/2025 | G11: 2462.14
A12: LOCALIZA | B12: ENI6B54 | C12: SAVEIRO ROBUST 1.6 8V TOTAL FLEX 2P C/AR | E12: 15/12/2022 | F12: 25/11/2025 | G12: 2462.14
A13: LOCALIZA | B13: EHE9A22 | C13: SAVEIRO ROBUST 1.6 8V TOTAL FLEX 2P C/AR | E13: 13/12/2022 | F13: 25/11/2025 | G13: 2462.14
... A893: LOCALIZA | B893: TDY0H02 | C893: FIORINO ENDURANCE FLEX 1.3 | E893: 13/05/2025 | F893: 13/05/2029 | G893: 3085
A894: MOVIDA | B894: OPP9E46 | C894: MOBI Like 1.0 Fire Flex 5p. | D894: LEVE | E894: 05/06/2024 | F894: 08/06/2027 | G894: 1730
A895: MOVIDA | B895: OPP9E47 | C895: MOBI Like 1.0 Fire Flex 5p. | D895: LEVE | E895: 18/06/2024 | F895: 21/06/2027 | G895: 1730
A896: MOVIDA | B896: OPP9E48 | C896: MOBI Like 1.0 Fire Flex 5p. | D896: LEVE | E896: 05/06/2024 | F896: 08/06/2027 | G896: 1730
A897: MOVIDA | B897: OPP9E49 | C897: MOBI Like 1.0 Fire Flex 5p. | D897: LEVE | E897: 05/06/2024 | F897: 08/06/2027 | G897: 1730
A898: MOVIDA | B898: OPP9E54 | C898: MOBI Like 1.0 Fire Flex 5p. | D898: LEVE | E898: 05/06/2024 | F898: 08/06/2027 | G898: 1730
A899: MOVIDA | B899: OPP9E64 | C899: MOBI Like 1.0 Fire Flex 5p. | D899: LEVE | E899: 18/06/2024 | F899: 21/06/2027 | G899: 1730
A900: MOVIDA | B900: OPP9E65 | C900: MOBI Like 1.0 Fire Flex 5p. | D900: LEVE | E900: 05/06/2024 | F900: 08/06/2027 | G900: 1730
A901: MOVIDA | B901: OPP9E67 | C901: MOBI Like 1.0 Fire Flex 5p. | D901: LEVE | E901: 05/06/2024 | F901: 08/06/2027 | G901: 1730
A902: MOVIDA | B902: OPP9E71 | C902: MOBI Like 1.0 Fire Flex 5p. | D902: LEVE | E902: 05/06/2024 | F902: 08/06/2027 | G902: 1730
A903: MOVIDA | B903: OPP9E72 | C903: MOBI Like 1.0 Fire Flex 5p. | D903: LEVE | E903: 18/06/2024 | F903: 21/06/2027 | G903: 1730
A904: MOVIDA | B904: OPP9E74 | C904: MOBI Like 1.0 Fire Flex 5p. | D904: LEVE | E904: 05/06/2024 | F904: 08/06/2027 | G904: 1730
A905: MOVIDA | B905: OPP9E75 | C905: MOBI Like 1.0 Fire Flex 5p. | D905: LEVE | E905: 18/06/2024 | F905: 21/06/2027 | G905: 1730
... A2086: MISTER | B2086: TLC6H25 | C2086: STONIC | D2086: SUV | E2086: 03/09/2024 | F2086: 03/09/2028 | G2086: 3745
